{"date":"2026-07-02","updatedAt":"09:10","kpi":{"spend":6294052,"purchases":287,"val":16244078,"roas":258.08617405766586},"byHour":[{"hour":"00:00","spend":1423408,"purchases":78,"val":4494350,"roas":315.745731371469},{"hour":"01:00","spend":939941,"purchases":57,"val":3154500,"roas":335.6061710256282},{"hour":"02:00","spend":620249,"purchases":29,"val":1581050,"roas":254.905691101477},{"hour":"03:00","spend":429994,"purchases":24,"val":1302042,"roas":302.8046902980042},{"hour":"04:00","spend":314978,"purchases":22,"val":1177486,"roas":373.8311882099702},{"hour":"05:00","spend":333615,"purchases":8,"val":496700,"roas":148.8841928570358},{"hour":"06:00","spend":464485,"purchases":15,"val":912800,"roas":196.51872503955994},{"hour":"07:00","spend":672341,"purchases":28,"val":1507350,"roas":224.1942704669208},{"hour":"08:00","spend":972657,"purchases":25,"val":1558500,"roas":160.2312017494348},{"hour":"09:00","spend":85589,"purchases":0,"val":0,"roas":0}],"byHourPerProduct":{"닭가슴살":[{"hour":"00:00","spend":160159,"purchases":4,"val":262550,"roas":163.93084372404923},{"hour":"01:00","spend":122256,"purchases":4,"val":363800,"roas":297.5723072896218},{"hour":"02:00","spend":91542,"purchases":4,"val":249600,"roas":272.66172904240676},{"hour":"03:00","spend":63534,"purchases":2,"val":119600,"roas":188.2456637391003},{"hour":"04:00","spend":49307,"purchases":1,"val":59800,"roas":121.28095402275538},{"hour":"05:00","spend":58715,"purchases":3,"val":224750,"roas":382.7812313718811},{"hour":"06:00","spend":80345,"purchases":2,"val":119500,"roas":148.73358640861284},{"hour":"07:00","spend":87445,"purchases":4,"val":253800,"roas":290.23957916404595},{"hour":"08:00","spend":99076,"purchases":3,"val":284000,"roas":286.6486333723606},{"hour":"09:00","spend":7924,"purchases":0,"val":0,"roas":0}],"크리스피닭가슴살":[{"hour":"00:00","spend":647571,"purchases":39,"val":2360400,"roas":364.50057213803586},{"hour":"01:00","spend":399626,"purchases":25,"val":1265600,"roas":316.6961108636575},{"hour":"02:00","spend":241802,"purchases":15,"val":829750,"roas":343.15266209543347},{"hour":"03:00","spend":166667,"purchases":10,"val":446950,"roas":268.16946366107265},{"hour":"04:00","spend":130012,"purchases":10,"val":530286,"roas":407.87465772390243},{"hour":"05:00","spend":137921,"purchases":3,"val":178350,"roas":129.31315753221045},{"hour":"06:00","spend":200357,"purchases":5,"val":315300,"roas":157.36909616334842},{"hour":"07:00","spend":340427,"purchases":11,"val":616350,"roas":181.05203171311325},{"hour":"08:00","spend":494930,"purchases":13,"val":624400,"roas":126.15925484411936},{"hour":"09:00","spend":41627,"purchases":0,"val":0,"roas":0}],"크리스피안심":[{"hour":"00:00","spend":102124,"purchases":4,"val":172500,"roas":168.91230269084642},{"hour":"01:00","spend":61280,"purchases":3,"val":170100,"roas":277.57832898172325},{"hour":"02:00","spend":34459,"purchases":2,"val":65900,"roas":191.2417655764822},{"hour":"03:00","spend":22469,"purchases":0,"val":0,"roas":0},{"hour":"04:00","spend":15780,"purchases":0,"val":0,"roas":0},{"hour":"05:00","spend":16555,"purchases":1,"val":44000,"roas":265.78073089700996},{"hour":"06:00","spend":12275,"purchases":1,"val":205900,"roas":1677.3930753564155},{"hour":"07:00","spend":20229,"purchases":2,"val":85700,"roas":423.6492164714025},{"hour":"08:00","spend":28221,"purchases":0,"val":0,"roas":0},{"hour":"09:00","spend":4235,"purchases":0,"val":0,"roas":0}],"안심폭탄볶음밥":[{"hour":"00:00","spend":107306,"purchases":7,"val":523700,"roas":488.0435390378916},{"hour":"01:00","spend":59454,"purchases":2,"val":248400,"roas":417.8019981834696},{"hour":"02:00","spend":38471,"purchases":0,"val":0,"roas":0},{"hour":"03:00","spend":29317,"purchases":2,"val":117000,"roas":399.08585462359724},{"hour":"04:00","spend":21576,"purchases":1,"val":64900,"roas":300.7971820541342},{"hour":"05:00","spend":17986,"purchases":0,"val":0,"roas":0},{"hour":"06:00","spend":22740,"purchases":0,"val":0,"roas":0},{"hour":"07:00","spend":43523,"purchases":3,"val":174500,"roas":400.937435378995},{"hour":"08:00","spend":57585,"purchases":2,"val":205900,"roas":357.5583919423461},{"hour":"09:00","spend":5593,"purchases":0,"val":0,"roas":0}],"닭다리":[{"hour":"00:00","spend":134021,"purchases":10,"val":552200,"roas":412.024981159669},{"hour":"01:00","spend":91364,"purchases":8,"val":430100,"roas":470.7543452563373},{"hour":"02:00","spend":55650,"purchases":3,"val":187800,"roas":337.46630727762806},{"hour":"03:00","spend":34069,"purchases":1,"val":50900,"roas":149.4026827908069},{"hour":"04:00","spend":25472,"purchases":2,"val":129200,"roas":507.22361809045225},{"hour":"05:00","spend":21230,"purchases":0,"val":0,"roas":0},{"hour":"06:00","spend":35690,"purchases":1,"val":48000,"roas":134.49145418884842},{"hour":"07:00","spend":69198,"purchases":3,"val":183800,"roas":265.6146131391081},{"hour":"08:00","spend":137385,"purchases":1,"val":50900,"roas":37.04916839538523},{"hour":"09:00","spend":11812,"purchases":0,"val":0,"roas":0}],"크리스피닭다리":[{"hour":"00:00","spend":43202,"purchases":2,"val":96900,"roas":224.29517151983706},{"hour":"01:00","spend":33343,"purchases":0,"val":0,"roas":0},{"hour":"02:00","spend":21918,"purchases":0,"val":0,"roas":0},{"hour":"03:00","spend":15261,"purchases":1,"val":69900,"roas":458.03027324552784},{"hour":"04:00","spend":11370,"purchases":0,"val":0,"roas":0},{"hour":"05:00","spend":10227,"purchases":0,"val":0,"roas":0},{"hour":"06:00","spend":17934,"purchases":0,"val":0,"roas":0},{"hour":"07:00","spend":17772,"purchases":0,"val":0,"roas":0},{"hour":"08:00","spend":23926,"purchases":0,"val":0,"roas":0},{"hour":"09:00","spend":1433,"purchases":0,"val":0,"roas":0}],"김자반밥바":[{"hour":"00:00","spend":209801,"purchases":12,"val":526100,"roas":250.7614358368168},{"hour":"01:00","spend":162499,"purchases":14,"val":616800,"roas":379.57156659425596},{"hour":"02:00","spend":127996,"purchases":5,"val":248000,"roas":193.7560548767149},{"hour":"03:00","spend":92105,"purchases":7,"val":437992,"roas":475.5355301015146},{"hour":"04:00","spend":57455,"purchases":7,"val":333600,"roas":580.6283178139413},{"hour":"05:00","spend":66161,"purchases":1,"val":49600,"roas":74.9686371124983},{"hour":"06:00","spend":87702,"purchases":6,"val":224100,"roas":255.52438940959158},{"hour":"07:00","spend":73650,"purchases":5,"val":193200,"roas":262.32179226069246},{"hour":"08:00","spend":116077,"purchases":6,"val":393300,"roas":338.82681323604163},{"hour":"09:00","spend":12200,"purchases":0,"val":0,"roas":0}],"통살+그릴드":[{"hour":"00:00","spend":19224,"purchases":0,"val":0,"roas":0},{"hour":"01:00","spend":10119,"purchases":1,"val":59700,"roas":589.9792469611622},{"hour":"02:00","spend":8411,"purchases":0,"val":0,"roas":0},{"hour":"03:00","spend":6572,"purchases":1,"val":59700,"roas":908.3992696287279},{"hour":"04:00","spend":4006,"purchases":1,"val":59700,"roas":1490.264603095357},{"hour":"05:00","spend":4820,"purchases":0,"val":0,"roas":0},{"hour":"06:00","spend":7442,"purchases":0,"val":0,"roas":0},{"hour":"07:00","spend":20097,"purchases":0,"val":0,"roas":0},{"hour":"08:00","spend":15457,"purchases":0,"val":0,"roas":0},{"hour":"09:00","spend":765,"purchases":0,"val":0,"roas":0}]},"byHourPerCampaign":{"01.통살(ASC)(101010)_TCPA16000_A+SC 캠페인_ALL_V1C7_수_표준기여_2336":[{"hour":"00:00","spend":45560,"purchases":1,"val":59800,"roas":131.25548726953468},{"hour":"01:00","spend":19247,"purchases":2,"val":128100,"roas":665.558268821115},{"hour":"02:00","spend":16141,"purchases":2,"val":130100,"roas":806.0219317266589},{"hour":"03:00","spend":13087,"purchases":1,"val":59800,"roas":456.9420035149385},{"hour":"04:00","spend":10578,"purchases":0,"val":0,"roas":0},{"hour":"05:00","spend":7657,"purchases":0,"val":0,"roas":0},{"hour":"06:00","spend":17081,"purchases":1,"val":59800,"roas":350.0965985598033},{"hour":"07:00","spend":31234,"purchases":3,"val":194100,"roas":621.4381763462893},{"hour":"08:00","spend":35637,"purchases":1,"val":48800,"roas":136.93633021859304},{"hour":"09:00","spend":2235,"purchases":0,"val":0,"roas":0}],"01.통살(ASC)(메가딜)_TCPA20000_A+SC 캠페인_ALL_V1C7_수_표준기여_1874":[{"hour":"00:00","spend":9863,"purchases":0,"val":0,"roas":0},{"hour":"01:00","spend":30613,"purchases":1,"val":59700,"roas":195.0151896253226},{"hour":"02:00","spend":27878,"purchases":1,"val":59800,"roas":214.50606212784274},{"hour":"03:00","spend":18556,"purchases":0,"val":0,"roas":0},{"hour":"04:00","spend":14250,"purchases":0,"val":0,"roas":0},{"hour":"05:00","spend":17618,"purchases":1,"val":69100,"roas":392.21250993302306},{"hour":"06:00","spend":3190,"purchases":0,"val":0,"roas":0},{"hour":"07:00","spend":7973,"purchases":0,"val":0,"roas":0},{"hour":"08:00","spend":9793,"purchases":0,"val":0,"roas":0},{"hour":"09:00","spend":1245,"purchases":0,"val":0,"roas":0}],"07.크리스피(ASC)(메가딜)_A+SC 캠페인_구매최적화_수_표준기여_2464":[{"hour":"00:00","spend":77957,"purchases":7,"val":371250,"roas":476.22407224495555},{"hour":"01:00","spend":36811,"purchases":4,"val":150500,"roas":408.845182146641},{"hour":"02:00","spend":22480,"purchases":1,"val":41700,"roas":185.4982206405694},{"hour":"03:00","spend":14093,"purchases":0,"val":0,"roas":0},{"hour":"04:00","spend":12026,"purchases":1,"val":57900,"roas":481.45684350573754},{"hour":"05:00","spend":9352,"purchases":0,"val":0,"roas":0},{"hour":"06:00","spend":17982,"purchases":1,"val":68500,"roas":380.9364920476031},{"hour":"07:00","spend":70580,"purchases":1,"val":42500,"roas":60.215358458486826},{"hour":"08:00","spend":89286,"purchases":2,"val":105500,"roas":118.15962188920996},{"hour":"09:00","spend":11892,"purchases":0,"val":0,"roas":0}],"07.크리스피(ASC)(메가딜)_TCPA16000_A+SC 캠페인_ALL_수_표준기여_2464":[{"hour":"00:00","spend":166564,"purchases":8,"val":377500,"roas":226.63960999975984},{"hour":"01:00","spend":108945,"purchases":2,"val":69500,"roas":63.79365735003901},{"hour":"02:00","spend":58407,"purchases":2,"val":51600,"roas":88.3455750166932},{"hour":"03:00","spend":34973,"purchases":1,"val":44000,"roas":125.81134017670774},{"hour":"04:00","spend":26023,"purchases":5,"val":218250,"roas":838.681166660262},{"hour":"05:00","spend":39688,"purchases":2,"val":106400,"roas":268.09111066317274},{"hour":"06:00","spend":16376,"purchases":1,"val":62600,"roas":382.266731802638},{"hour":"07:00","spend":16295,"purchases":0,"val":0,"roas":0},{"hour":"08:00","spend":26574,"purchases":3,"val":122300,"roas":460.22427937081363},{"hour":"09:00","spend":928,"purchases":0,"val":0,"roas":0}],"01.통살(ASC)(101010)_A+SC 캠페인_ALL_V1C7_수_표준기여_2336_AI":[{"hour":"00:00","spend":32632,"purchases":0,"val":0,"roas":0},{"hour":"01:00","spend":18987,"purchases":0,"val":0,"roas":0},{"hour":"02:00","spend":12096,"purchases":0,"val":0,"roas":0},{"hour":"03:00","spend":8986,"purchases":0,"val":0,"roas":0},{"hour":"04:00","spend":10422,"purchases":0,"val":0,"roas":0},{"hour":"05:00","spend":13349,"purchases":0,"val":0,"roas":0},{"hour":"06:00","spend":26061,"purchases":0,"val":0,"roas":0},{"hour":"07:00","spend":5274,"purchases":0,"val":0,"roas":0},{"hour":"08:00","spend":6396,"purchases":1,"val":182300,"roas":2850.2188868042526},{"hour":"09:00","spend":579,"purchases":0,"val":0,"roas":0}],"01.통살(ASC)(101010)_TCPA16000_A+SC 캠페인_ALL_V1C7_수_표준기여_2336_02":[{"hour":"00:00","spend":4813,"purchases":0,"val":0,"roas":0},{"hour":"01:00","spend":4376,"purchases":0,"val":0,"roas":0},{"hour":"02:00","spend":1958,"purchases":0,"val":0,"roas":0},{"hour":"03:00","spend":1357,"purchases":0,"val":0,"roas":0},{"hour":"04:00","spend":938,"purchases":0,"val":0,"roas":0},{"hour":"05:00","spend":777,"purchases":0,"val":0,"roas":0},{"hour":"06:00","spend":1507,"purchases":0,"val":0,"roas":0},{"hour":"07:00","spend":2547,"purchases":0,"val":0,"roas":0},{"hour":"08:00","spend":3568,"purchases":0,"val":0,"roas":0},{"hour":"09:00","spend":295,"purchases":0,"val":0,"roas":0}],"07.크리스피(ASC)(101010)_A+SC 캠페인_구매최적화_수_표준기여_2659_260322":[{"hour":"00:00","spend":14266,"purchases":0,"val":0,"roas":0},{"hour":"01:00","spend":5362,"purchases":0,"val":0,"roas":0},{"hour":"02:00","spend":2226,"purchases":0,"val":0,"roas":0},{"hour":"03:00","spend":1994,"purchases":0,"val":0,"roas":0},{"hour":"04:00","spend":2540,"purchases":0,"val":0,"roas":0},{"hour":"05:00","spend":2226,"purchases":0,"val":0,"roas":0},{"hour":"06:00","spend":2917,"purchases":0,"val":0,"roas":0},{"hour":"07:00","spend":4293,"purchases":0,"val":0,"roas":0},{"hour":"08:00","spend":10344,"purchases":1,"val":66000,"roas":638.0510440835267},{"hour":"09:00","spend":1007,"purchases":0,"val":0,"roas":0}],"16.안심크리스피(ASC)(메가딜)_A+SC 캠페인_구매최적화_수_표준기여_2863_260327":[{"hour":"00:00","spend":0,"purchases":0,"val":0,"roas":0},{"hour":"01:00","spend":0,"purchases":0,"val":0,"roas":0}],"16.안심크리스피(ASC)(메가딜)_TCPA14000_A+SC 캠페인_ALL_C7_수_표준기여_2863_260327":[{"hour":"00:00","spend":79948,"purchases":3,"val":146600,"roas":183.36918997348278},{"hour":"01:00","spend":50722,"purchases":3,"val":170100,"roas":335.3574385868065},{"hour":"02:00","spend":27541,"purchases":2,"val":65900,"roas":239.279619476417},{"hour":"03:00","spend":17949,"purchases":0,"val":0,"roas":0},{"hour":"04:00","spend":12558,"purchases":0,"val":0,"roas":0},{"hour":"05:00","spend":13095,"purchases":0,"val":0,"roas":0},{"hour":"06:00","spend":5962,"purchases":1,"val":205900,"roas":3453.539080845354},{"hour":"07:00","spend":6566,"purchases":1,"val":41000,"roas":624.4288760280232},{"hour":"08:00","spend":9588,"purchases":0,"val":0,"roas":0},{"hour":"09:00","spend":2667,"purchases":0,"val":0,"roas":0}],"07.크리스피(ASC)(메가딜)_TCPA16000_A+SC 캠페인_ALL_수_표준기여_2464_260403":[{"hour":"00:00","spend":24213,"purchases":4,"val":513200,"roas":2119.5225705199687},{"hour":"01:00","spend":18824,"purchases":0,"val":0,"roas":0},{"hour":"02:00","spend":15622,"purchases":1,"val":60500,"roas":387.2743566764819},{"hour":"03:00","spend":13996,"purchases":1,"val":93800,"roas":670.1914832809374},{"hour":"04:00","spend":12918,"purchases":0,"val":0,"roas":0},{"hour":"05:00","spend":12960,"purchases":1,"val":71950,"roas":555.1697530864197},{"hour":"06:00","spend":16698,"purchases":0,"val":0,"roas":0},{"hour":"07:00","spend":27447,"purchases":1,"val":25800,"roas":93.99934419062193},{"hour":"08:00","spend":39011,"purchases":0,"val":0,"roas":0},{"hour":"09:00","spend":3774,"purchases":0,"val":0,"roas":0}],"01.통살(ASC)(101010)_TCPA16000_A+SC 캠페인_ALL_V1C7_수_표준기여_2336_03":[{"hour":"00:00","spend":5934,"purchases":0,"val":0,"roas":0},{"hour":"01:00","spend":16447,"purchases":0,"val":0,"roas":0},{"hour":"02:00","spend":10583,"purchases":1,"val":59700,"roas":564.1122555041104},{"hour":"03:00","spend":7363,"purchases":0,"val":0,"roas":0},{"hour":"04:00","spend":4729,"purchases":1,"val":59800,"roas":1264.5379572848383},{"hour":"05:00","spend":5997,"purchases":0,"val":0,"roas":0},{"hour":"06:00","spend":9201,"purchases":1,"val":59700,"roas":648.8425171177046},{"hour":"07:00","spend":1263,"purchases":1,"val":59700,"roas":4726.840855106888},{"hour":"08:00","spend":6202,"purchases":0,"val":0,"roas":0},{"hour":"09:00","spend":658,"purchases":0,"val":0,"roas":0}],"07.크리스피(ASC)(메가딜)_A+SC 캠페인_구매최적화_수_표준기여_2464_260404":[{"hour":"00:00","spend":55775,"purchases":5,"val":337000,"roas":604.2133572389063},{"hour":"01:00","spend":34205,"purchases":6,"val":191900,"roas":561.0290893144277},{"hour":"02:00","spend":20767,"purchases":0,"val":0,"roas":0},{"hour":"03:00","spend":15039,"purchases":2,"val":69800,"roas":464.1266041625108},{"hour":"04:00","spend":13873,"purchases":0,"val":0,"roas":0},{"hour":"05:00","spend":6901,"purchases":0,"val":0,"roas":0},{"hour":"06:00","spend":6456,"purchases":0,"val":0,"roas":0},{"hour":"07:00","spend":51817,"purchases":0,"val":0,"roas":0},{"hour":"08:00","spend":81576,"purchases":1,"val":35600,"roas":43.64028635873296},{"hour":"09:00","spend":6065,"purchases":0,"val":0,"roas":0}],"17.안심볶음밥(ASC)(메가딜)_TCPA_A+SC 캠페인_ALL_C7_수_표준기여_2903_260409":[{"hour":"00:00","spend":31569,"purchases":1,"val":104400,"roas":330.7041718141214},{"hour":"01:00","spend":19846,"purchases":0,"val":0,"roas":0},{"hour":"02:00","spend":13450,"purchases":0,"val":0,"roas":0},{"hour":"03:00","spend":13015,"purchases":1,"val":93000,"roas":714.5601229350749},{"hour":"04:00","spend":8063,"purchases":0,"val":0,"roas":0},{"hour":"05:00","spend":7532,"purchases":0,"val":0,"roas":0},{"hour":"06:00","spend":3617,"purchases":0,"val":0,"roas":0},{"hour":"07:00","spend":3245,"purchases":0,"val":0,"roas":0},{"hour":"08:00","spend":6842,"purchases":0,"val":0,"roas":0},{"hour":"09:00","spend":215,"purchases":0,"val":0,"roas":0}],"01.통살(ASC)(101010)_TCPA_A+SC 캠페인_ALL_C7_수_표준기여_2336_260410_intern":[{"hour":"00:00","spend":6743,"purchases":0,"val":0,"roas":0},{"hour":"01:00","spend":3033,"purchases":0,"val":0,"roas":0},{"hour":"02:00","spend":2733,"purchases":0,"val":0,"roas":0},{"hour":"03:00","spend":1124,"purchases":1,"val":59800,"roas":5320.284697508897},{"hour":"04:00","spend":380,"purchases":0,"val":0,"roas":0},{"hour":"05:00","spend":628,"purchases":0,"val":0,"roas":0},{"hour":"06:00","spend":2156,"purchases":0,"val":0,"roas":0},{"hour":"07:00","spend":6024,"purchases":0,"val":0,"roas":0},{"hour":"08:00","spend":5467,"purchases":0,"val":0,"roas":0},{"hour":"09:00","spend":484,"purchases":0,"val":0,"roas":0}],"01.통살(ASC)(101010)_A+SC 캠페인_구매최적화_수_표준기여_2336_260410_intern":[{"hour":"00:00","spend":4667,"purchases":0,"val":0,"roas":0},{"hour":"01:00","spend":2359,"purchases":0,"val":0,"roas":0},{"hour":"02:00","spend":2245,"purchases":0,"val":0,"roas":0},{"hour":"03:00","spend":961,"purchases":0,"val":0,"roas":0},{"hour":"04:00","spend":880,"purchases":0,"val":0,"roas":0},{"hour":"05:00","spend":977,"purchases":0,"val":0,"roas":0},{"hour":"06:00","spend":2424,"purchases":0,"val":0,"roas":0},{"hour":"07:00","spend":4768,"purchases":0,"val":0,"roas":0},{"hour":"08:00","spend":5717,"purchases":0,"val":0,"roas":0},{"hour":"09:00","spend":465,"purchases":0,"val":0,"roas":0}],"03.닭다리살(ASC)(101010)_A+SC 캠페인_구매최적화_수_표준기여_2358_260410_intern":[{"hour":"00:00","spend":30283,"purchases":2,"val":129600,"roas":427.962883465971},{"hour":"01:00","spend":18040,"purchases":0,"val":0,"roas":0},{"hour":"02:00","spend":13973,"purchases":1,"val":70900,"roas":507.4071423459529},{"hour":"03:00","spend":8961,"purchases":0,"val":0,"roas":0},{"hour":"04:00","spend":4220,"purchases":0,"val":0,"roas":0},{"hour":"05:00","spend":3726,"purchases":0,"val":0,"roas":0},{"hour":"06:00","spend":6695,"purchases":0,"val":0,"roas":0},{"hour":"07:00","spend":17397,"purchases":0,"val":0,"roas":0},{"hour":"08:00","spend":32410,"purchases":0,"val":0,"roas":0},{"hour":"09:00","spend":13,"purchases":0,"val":0,"roas":0}],"07.크리스피(ASC)(메가딜)_A+SC 캠페인_구매최적화_수_표준기여_2464_260404_test":[{"hour":"00:00","spend":55027,"purchases":4,"val":126700,"roas":230.25060424882332},{"hour":"01:00","spend":23948,"purchases":3,"val":119700,"roas":499.832971438116},{"hour":"02:00","spend":15904,"purchases":2,"val":127700,"roas":802.9426559356137},{"hour":"03:00","spend":12478,"purchases":3,"val":119900,"roas":960.8911684564835},{"hour":"04:00","spend":11792,"purchases":0,"val":0,"roas":0},{"hour":"05:00","spend":12737,"purchases":0,"val":0,"roas":0},{"hour":"06:00","spend":30251,"purchases":0,"val":0,"roas":0},{"hour":"07:00","spend":45114,"purchases":2,"val":87950,"roas":194.9505696679523},{"hour":"08:00","spend":53288,"purchases":2,"val":71500,"roas":134.17655006755743},{"hour":"09:00","spend":6250,"purchases":0,"val":0,"roas":0}],"07.크리스피(ASC)(메가딜)_A+SC 캠페인_구매최적화_수_표준기여_2464_260416_intern":[{"hour":"00:00","spend":38843,"purchases":2,"val":88500,"roas":227.84028010194888},{"hour":"01:00","spend":22813,"purchases":4,"val":282100,"roas":1236.5756366983737},{"hour":"02:00","spend":18481,"purchases":3,"val":217800,"roas":1178.5076565120935},{"hour":"03:00","spend":12054,"purchases":1,"val":37200,"roas":308.6112493777999},{"hour":"04:00","spend":9132,"purchases":0,"val":0,"roas":0},{"hour":"05:00","spend":10313,"purchases":0,"val":0,"roas":0},{"hour":"06:00","spend":19025,"purchases":1,"val":60000,"roas":315.37450722733246},{"hour":"07:00","spend":50701,"purchases":4,"val":228100,"roas":449.89250705114296},{"hour":"08:00","spend":71384,"purchases":3,"val":165400,"roas":231.70458366020398},{"hour":"09:00","spend":6966,"purchases":0,"val":0,"roas":0}],"07.크리스피(ASC)(메가딜)_TCPA14000_A+SC 캠페인_ALL_C7_수_표준기여_2464_260416_intern":[{"hour":"00:00","spend":40006,"purchases":1,"val":83900,"roas":209.71854221866718},{"hour":"01:00","spend":33194,"purchases":1,"val":153700,"roas":463.03548834126656},{"hour":"02:00","spend":20237,"purchases":0,"val":0,"roas":0},{"hour":"03:00","spend":13668,"purchases":0,"val":0,"roas":0},{"hour":"04:00","spend":6451,"purchases":3,"val":210236,"roas":3258.9676019221824},{"hour":"05:00","spend":5506,"purchases":0,"val":0,"roas":0},{"hour":"06:00","spend":16822,"purchases":0,"val":0,"roas":0},{"hour":"07:00","spend":34269,"purchases":2,"val":161600,"roas":471.5632204032799},{"hour":"08:00","spend":66564,"purchases":1,"val":58100,"roas":87.28441800372573}],"18.크리스피닭다리(ASC)_TCPA14000_A+SC 캠페인_ALL_C7_수_표준기여_2910_260525":[{"hour":"00:00","spend":5368,"purchases":0,"val":0,"roas":0},{"hour":"01:00","spend":5268,"purchases":0,"val":0,"roas":0},{"hour":"02:00","spend":3983,"purchases":0,"val":0,"roas":0},{"hour":"03:00","spend":4362,"purchases":0,"val":0,"roas":0},{"hour":"04:00","spend":2687,"purchases":0,"val":0,"roas":0},{"hour":"05:00","spend":1819,"purchases":0,"val":0,"roas":0},{"hour":"06:00","spend":2340,"purchases":0,"val":0,"roas":0},{"hour":"07:00","spend":2798,"purchases":0,"val":0,"roas":0},{"hour":"08:00","spend":4421,"purchases":0,"val":0,"roas":0},{"hour":"09:00","spend":301,"purchases":0,"val":0,"roas":0}],"18.크리스피닭다리(ASC)_A+SC 캠페인_구매최적화_수_표준기여_2910_260416_intern(광고소진후종료)":[{"hour":"00:00","spend":1766,"purchases":0,"val":0,"roas":0},{"hour":"01:00","spend":1624,"purchases":0,"val":0,"roas":0},{"hour":"02:00","spend":843,"purchases":0,"val":0,"roas":0},{"hour":"03:00","spend":881,"purchases":1,"val":69900,"roas":7934.16572077185},{"hour":"04:00","spend":666,"purchases":0,"val":0,"roas":0},{"hour":"05:00","spend":857,"purchases":0,"val":0,"roas":0},{"hour":"06:00","spend":2834,"purchases":0,"val":0,"roas":0},{"hour":"07:00","spend":1979,"purchases":0,"val":0,"roas":0},{"hour":"08:00","spend":3034,"purchases":0,"val":0,"roas":0},{"hour":"09:00","spend":141,"purchases":0,"val":0,"roas":0}],"18.크리스피닭다리(ASC)_TCPA14000_A+SC 캠페인_ALL_C7_수_표준기여_2910_260416":[{"hour":"00:00","spend":6973,"purchases":1,"val":54900,"roas":787.3225297576366},{"hour":"01:00","spend":4724,"purchases":0,"val":0,"roas":0},{"hour":"02:00","spend":3136,"purchases":0,"val":0,"roas":0},{"hour":"03:00","spend":1894,"purchases":0,"val":0,"roas":0},{"hour":"04:00","spend":1499,"purchases":0,"val":0,"roas":0},{"hour":"05:00","spend":1083,"purchases":0,"val":0,"roas":0},{"hour":"06:00","spend":1554,"purchases":0,"val":0,"roas":0},{"hour":"07:00","spend":4755,"purchases":0,"val":0,"roas":0},{"hour":"08:00","spend":6875,"purchases":0,"val":0,"roas":0},{"hour":"09:00","spend":343,"purchases":0,"val":0,"roas":0}],"18.크리스피닭다리(ASC)_A+SC 캠페인_구매최적화_수_표준기여_2910_260416":[{"hour":"00:00","spend":2983,"purchases":0,"val":0,"roas":0},{"hour":"01:00","spend":1309,"purchases":0,"val":0,"roas":0},{"hour":"02:00","spend":397,"purchases":0,"val":0,"roas":0},{"hour":"03:00","spend":397,"purchases":0,"val":0,"roas":0},{"hour":"04:00","spend":667,"purchases":0,"val":0,"roas":0},{"hour":"05:00","spend":947,"purchases":0,"val":0,"roas":0},{"hour":"06:00","spend":1940,"purchases":0,"val":0,"roas":0},{"hour":"07:00","spend":1906,"purchases":0,"val":0,"roas":0},{"hour":"08:00","spend":1923,"purchases":0,"val":0,"roas":0},{"hour":"09:00","spend":20,"purchases":0,"val":0,"roas":0}],"07.크리스피(ASC)(101010)_TCPA14000_A+SC 캠페인_ALL_C7_수_표준기여_2659_260424_intern":[{"hour":"00:00","spend":4697,"purchases":0,"val":0,"roas":0},{"hour":"01:00","spend":2426,"purchases":0,"val":0,"roas":0},{"hour":"02:00","spend":2702,"purchases":0,"val":0,"roas":0},{"hour":"03:00","spend":2804,"purchases":0,"val":0,"roas":0},{"hour":"04:00","spend":1409,"purchases":0,"val":0,"roas":0},{"hour":"05:00","spend":1080,"purchases":0,"val":0,"roas":0},{"hour":"06:00","spend":2639,"purchases":0,"val":0,"roas":0},{"hour":"07:00","spend":5185,"purchases":0,"val":0,"roas":0},{"hour":"08:00","spend":6493,"purchases":0,"val":0,"roas":0},{"hour":"09:00","spend":254,"purchases":0,"val":0,"roas":0}],"03.닭다리살(ASC)(101010)_A+SC 캠페인_구매최적화_값_표준기여_2358":[{"hour":"00:00","spend":3388,"purchases":0,"val":0,"roas":0},{"hour":"01:00","spend":1700,"purchases":1,"val":71000,"roas":4176.470588235295},{"hour":"02:00","spend":1803,"purchases":0,"val":0,"roas":0},{"hour":"03:00","spend":614,"purchases":0,"val":0,"roas":0},{"hour":"04:00","spend":383,"purchases":0,"val":0,"roas":0},{"hour":"05:00","spend":567,"purchases":0,"val":0,"roas":0},{"hour":"06:00","spend":1903,"purchases":0,"val":0,"roas":0},{"hour":"07:00","spend":3369,"purchases":1,"val":73500,"roas":2181.6562778272482},{"hour":"08:00","spend":2759,"purchases":0,"val":0,"roas":0},{"hour":"09:00","spend":391,"purchases":0,"val":0,"roas":0}],"17.안심볶음밥(ASC)(메가딜)_A+SC 캠페인_구매최적화_수_표준기여_2903_260507_남자":[{"hour":"00:00","spend":23737,"purchases":3,"val":187400,"roas":789.4847706112819},{"hour":"01:00","spend":12660,"purchases":1,"val":62600,"roas":494.47077409162716},{"hour":"02:00","spend":9106,"purchases":0,"val":0,"roas":0},{"hour":"03:00","spend":5966,"purchases":1,"val":24000,"roas":402.2795843110962},{"hour":"04:00","spend":4525,"purchases":0,"val":0,"roas":0},{"hour":"05:00","spend":2626,"purchases":0,"val":0,"roas":0},{"hour":"06:00","spend":3978,"purchases":0,"val":0,"roas":0},{"hour":"07:00","spend":17524,"purchases":1,"val":24000,"roas":136.95503309746633},{"hour":"08:00","spend":22787,"purchases":0,"val":0,"roas":0},{"hour":"09:00","spend":2772,"purchases":0,"val":0,"roas":0}],"17.안심볶음밥(ASC)(메가딜)_A+SC 캠페인_구매최적화_수_표준기여_2903_260507_남자_02":[{"hour":"00:00","spend":5559,"purchases":0,"val":0,"roas":0},{"hour":"01:00","spend":3873,"purchases":0,"val":0,"roas":0},{"hour":"02:00","spend":1960,"purchases":0,"val":0,"roas":0},{"hour":"03:00","spend":1240,"purchases":0,"val":0,"roas":0},{"hour":"04:00","spend":1398,"purchases":0,"val":0,"roas":0},{"hour":"05:00","spend":1121,"purchases":0,"val":0,"roas":0},{"hour":"06:00","spend":1271,"purchases":0,"val":0,"roas":0},{"hour":"07:00","spend":1080,"purchases":0,"val":0,"roas":0},{"hour":"08:00","spend":2854,"purchases":0,"val":0,"roas":0},{"hour":"09:00","spend":126,"purchases":0,"val":0,"roas":0}],"07.크리스피(ASC)(통합)_A+SC 캠페인_구매최적화_수_표준기여_통합_260511":[{"hour":"00:00","spend":66430,"purchases":1,"val":34750,"roas":52.31070299563451},{"hour":"01:00","spend":27003,"purchases":2,"val":172300,"roas":638.0772506758508},{"hour":"02:00","spend":13219,"purchases":1,"val":43250,"roas":327.1805734170512},{"hour":"03:00","spend":11286,"purchases":1,"val":41650,"roas":369.0412900939217},{"hour":"04:00","spend":9742,"purchases":0,"val":0,"roas":0},{"hour":"05:00","spend":12282,"purchases":0,"val":0,"roas":0},{"hour":"06:00","spend":25673,"purchases":2,"val":124200,"roas":483.7767304171698},{"hour":"07:00","spend":10069,"purchases":0,"val":0,"roas":0},{"hour":"08:00","spend":14349,"purchases":0,"val":0,"roas":0},{"hour":"09:00","spend":1074,"purchases":0,"val":0,"roas":0}],"16.안심크리스피(ASC)(메가딜)_TROAS_A+SC 캠페인_구매최적화_값_표준기여_2908_260518":[{"hour":"00:00","spend":10415,"purchases":0,"val":0,"roas":0},{"hour":"01:00","spend":4102,"purchases":0,"val":0,"roas":0},{"hour":"02:00","spend":3318,"purchases":0,"val":0,"roas":0},{"hour":"03:00","spend":2343,"purchases":0,"val":0,"roas":0},{"hour":"04:00","spend":1879,"purchases":0,"val":0,"roas":0},{"hour":"05:00","spend":1801,"purchases":0,"val":0,"roas":0},{"hour":"06:00","spend":2697,"purchases":0,"val":0,"roas":0},{"hour":"07:00","spend":5983,"purchases":0,"val":0,"roas":0},{"hour":"08:00","spend":7369,"purchases":0,"val":0,"roas":0},{"hour":"09:00","spend":677,"purchases":0,"val":0,"roas":0}],"18.크리스피닭다리(ASC)_TROAS_A+SC 캠페인_구매최적화_값_표준기여_2910_260518":[{"hour":"00:00","spend":20419,"purchases":1,"val":42000,"roas":205.69077819677753},{"hour":"01:00","spend":15209,"purchases":0,"val":0,"roas":0},{"hour":"02:00","spend":8825,"purchases":0,"val":0,"roas":0},{"hour":"03:00","spend":5708,"purchases":0,"val":0,"roas":0},{"hour":"04:00","spend":4048,"purchases":0,"val":0,"roas":0},{"hour":"05:00","spend":3704,"purchases":0,"val":0,"roas":0},{"hour":"06:00","spend":7605,"purchases":0,"val":0,"roas":0},{"hour":"07:00","spend":3961,"purchases":0,"val":0,"roas":0},{"hour":"08:00","spend":4460,"purchases":0,"val":0,"roas":0},{"hour":"09:00","spend":360,"purchases":0,"val":0,"roas":0}],"03.닭다리살(ASC)(1010)_A+SC캠페인_구매최적화_수_표준기여_2604_260519":[{"hour":"00:00","spend":60078,"purchases":5,"val":266100,"roas":442.9241985418956},{"hour":"01:00","spend":42906,"purchases":6,"val":300800,"roas":701.0674497739244},{"hour":"02:00","spend":23880,"purchases":2,"val":116900,"roas":489.53098827470683},{"hour":"03:00","spend":14226,"purchases":1,"val":50900,"roas":357.7955855475889},{"hour":"04:00","spend":10326,"purchases":0,"val":0,"roas":0},{"hour":"05:00","spend":7422,"purchases":0,"val":0,"roas":0},{"hour":"06:00","spend":10317,"purchases":0,"val":0,"roas":0},{"hour":"07:00","spend":24382,"purchases":0,"val":0,"roas":0},{"hour":"08:00","spend":71182,"purchases":1,"val":50900,"roas":71.5068416172628},{"hour":"09:00","spend":8064,"purchases":0,"val":0,"roas":0}],"03.닭다리살(ASC)(1010)_TROAS_A+SC캠페인_구매최적화_값_표준기여_2604_260519":[{"hour":"00:00","spend":24659,"purchases":1,"val":50900,"roas":206.4155075226084},{"hour":"01:00","spend":19467,"purchases":1,"val":58300,"roas":299.481173267581},{"hour":"02:00","spend":11758,"purchases":0,"val":0,"roas":0},{"hour":"03:00","spend":7297,"purchases":0,"val":0,"roas":0},{"hour":"04:00","spend":6000,"purchases":1,"val":67900,"roas":1131.6666666666667},{"hour":"05:00","spend":6559,"purchases":0,"val":0,"roas":0},{"hour":"06:00","spend":10416,"purchases":1,"val":48000,"roas":460.8294930875576},{"hour":"07:00","spend":15898,"purchases":2,"val":110300,"roas":693.7979620077997},{"hour":"08:00","spend":19293,"purchases":0,"val":0,"roas":0},{"hour":"09:00","spend":2380,"purchases":0,"val":0,"roas":0}],"03.닭다리살(ASC)(1010)_TCPA_A+SC캠페인_ALL_C7_수_표준기여_2604_260519":[{"hour":"00:00","spend":7850,"purchases":1,"val":50900,"roas":648.4076433121019},{"hour":"01:00","spend":5389,"purchases":0,"val":0,"roas":0},{"hour":"02:00","spend":3128,"purchases":0,"val":0,"roas":0},{"hour":"03:00","spend":2102,"purchases":0,"val":0,"roas":0},{"hour":"04:00","spend":4117,"purchases":1,"val":61300,"roas":1488.9482632985184},{"hour":"05:00","spend":1461,"purchases":0,"val":0,"roas":0},{"hour":"06:00","spend":2627,"purchases":0,"val":0,"roas":0},{"hour":"07:00","spend":2699,"purchases":0,"val":0,"roas":0},{"hour":"08:00","spend":6051,"purchases":0,"val":0,"roas":0},{"hour":"09:00","spend":597,"purchases":0,"val":0,"roas":0}],"20.김자반밥(ASC)(메가딜)_TCPA_A+SC캠페인_ALL_C7_수_표준기여_3003_260527":[{"hour":"00:00","spend":33843,"purchases":2,"val":99200,"roas":293.11822237981266},{"hour":"01:00","spend":25378,"purchases":4,"val":166400,"roas":655.6860272677122},{"hour":"02:00","spend":18363,"purchases":2,"val":99200,"roas":540.2167401840658},{"hour":"03:00","spend":11734,"purchases":0,"val":0,"roas":0},{"hour":"04:00","spend":8108,"purchases":0,"val":0,"roas":0},{"hour":"05:00","spend":10016,"purchases":1,"val":49600,"roas":495.2076677316294},{"hour":"06:00","spend":21803,"purchases":3,"val":114400,"roas":524.6984359950466},{"hour":"07:00","spend":39561,"purchases":2,"val":101400,"roas":256.31303556532947},{"hour":"08:00","spend":52600,"purchases":2,"val":68100,"roas":129.46768060836501},{"hour":"09:00","spend":3779,"purchases":0,"val":0,"roas":0}],"20.김자반밥바(ASC)(메가딜)_TROAS_A+SC캠페인_구매최적화_값_표준기여_3003_260527":[{"hour":"00:00","spend":129758,"purchases":4,"val":198400,"roas":152.90001387197708},{"hour":"01:00","spend":109015,"purchases":10,"val":450400,"roas":413.1541530981975},{"hour":"02:00","spend":92298,"purchases":3,"val":148800,"roas":161.21692777741663},{"hour":"03:00","spend":67307,"purchases":5,"val":358592,"roas":532.7707370704385},{"hour":"04:00","spend":38876,"purchases":5,"val":274000,"roas":704.805021092705},{"hour":"05:00","spend":47061,"purchases":0,"val":0,"roas":0},{"hour":"06:00","spend":48522,"purchases":3,"val":109700,"roas":226.08301389060634},{"hour":"07:00","spend":24211,"purchases":3,"val":91800,"roas":379.16649456858454},{"hour":"08:00","spend":48548,"purchases":2,"val":245800,"roas":506.3030402900223},{"hour":"09:00","spend":6514,"purchases":0,"val":0,"roas":0}],"20.김자반밥바(ASC)(메가딜)_A+SC캠페인_구매최적화_수_표준기여_3003_260527":[{"hour":"00:00","spend":42441,"purchases":6,"val":228500,"roas":538.3944770387126},{"hour":"01:00","spend":25319,"purchases":0,"val":0,"roas":0},{"hour":"02:00","spend":15377,"purchases":0,"val":0,"roas":0},{"hour":"03:00","spend":11092,"purchases":1,"val":49600,"roas":447.1691309051569},{"hour":"04:00","spend":8533,"purchases":2,"val":59600,"roas":698.4647837806165},{"hour":"05:00","spend":8187,"purchases":0,"val":0,"roas":0},{"hour":"06:00","spend":15957,"purchases":0,"val":0,"roas":0},{"hour":"07:00","spend":6942,"purchases":0,"val":0,"roas":0},{"hour":"08:00","spend":10242,"purchases":1,"val":49600,"roas":484.2804139816442},{"hour":"09:00","spend":1702,"purchases":0,"val":0,"roas":0}],"07.크리스피(ASC)(1010)_A+SC캠페인_구매최적화_수_표준기여_2992_260527":[{"hour":"00:00","spend":4821,"purchases":0,"val":0,"roas":0},{"hour":"01:00","spend":4311,"purchases":0,"val":0,"roas":0},{"hour":"02:00","spend":835,"purchases":0,"val":0,"roas":0},{"hour":"03:00","spend":1232,"purchases":0,"val":0,"roas":0},{"hour":"04:00","spend":134,"purchases":0,"val":0,"roas":0},{"hour":"05:00","spend":158,"purchases":0,"val":0,"roas":0},{"hour":"06:00","spend":2422,"purchases":0,"val":0,"roas":0},{"hour":"07:00","spend":7320,"purchases":1,"val":70400,"roas":961.7486338797814},{"hour":"08:00","spend":4603,"purchases":0,"val":0,"roas":0},{"hour":"09:00","spend":259,"purchases":0,"val":0,"roas":0}],"07.크리스피(ASC)(1010)_TROAS_A+SC캠페인_구매최적화_값_표준기여_2992_260527":[{"hour":"00:00","spend":88573,"purchases":7,"val":427600,"roas":482.765628351755},{"hour":"01:00","spend":76459,"purchases":3,"val":125900,"roas":164.6634143789482},{"hour":"02:00","spend":46621,"purchases":4,"val":241800,"roas":518.6503935994508},{"hour":"03:00","spend":28987,"purchases":1,"val":40600,"roas":140.0627867664815},{"hour":"04:00","spend":20974,"purchases":0,"val":0,"roas":0},{"hour":"05:00","spend":20445,"purchases":0,"val":0,"roas":0},{"hour":"06:00","spend":34874,"purchases":0,"val":0,"roas":0},{"hour":"07:00","spend":3772,"purchases":0,"val":0,"roas":0},{"hour":"08:00","spend":17565,"purchases":0,"val":0,"roas":0},{"hour":"09:00","spend":1681,"purchases":0,"val":0,"roas":0}],"07.크리스피(ASC)(1010)_TCPA_A+SC캠페인_ALL_C7_수_표준기여_2992_260705":[{"hour":"00:00","spend":177,"purchases":0,"val":0,"roas":0},{"hour":"01:00","spend":118,"purchases":0,"val":0,"roas":0},{"hour":"02:00","spend":6,"purchases":0,"val":0,"roas":0},{"hour":"03:00","spend":65,"purchases":0,"val":0,"roas":0},{"hour":"04:00","spend":123,"purchases":0,"val":0,"roas":0},{"hour":"05:00","spend":133,"purchases":0,"val":0,"roas":0},{"hour":"06:00","spend":160,"purchases":0,"val":0,"roas":0},{"hour":"07:00","spend":1921,"purchases":0,"val":0,"roas":0},{"hour":"08:00","spend":4706,"purchases":0,"val":0,"roas":0},{"hour":"09:00","spend":620,"purchases":0,"val":0,"roas":0}],"20.김자반밥바(ASC)(메가딜)_A+SC캠페인_구매최적화_수_표준기여_3003_260603":[{"hour":"00:00","spend":3759,"purchases":0,"val":0,"roas":0},{"hour":"01:00","spend":2787,"purchases":0,"val":0,"roas":0},{"hour":"02:00","spend":1958,"purchases":0,"val":0,"roas":0},{"hour":"03:00","spend":1972,"purchases":1,"val":29800,"roas":1511.1561866125762},{"hour":"04:00","spend":1938,"purchases":0,"val":0,"roas":0},{"hour":"05:00","spend":897,"purchases":0,"val":0,"roas":0},{"hour":"06:00","spend":1420,"purchases":0,"val":0,"roas":0},{"hour":"07:00","spend":2936,"purchases":0,"val":0,"roas":0},{"hour":"08:00","spend":4687,"purchases":1,"val":29800,"roas":635.8011521228932},{"hour":"09:00","spend":205,"purchases":0,"val":0,"roas":0}],"17.안심볶음밥(ASC)(메가딜)_A+SC 캠페인_구매최적화_수_표준기여_2903_260609_남자(가치조정)":[{"hour":"00:00","spend":24732,"purchases":2,"val":186000,"roas":752.0621057738962},{"hour":"01:00","spend":12521,"purchases":0,"val":0,"roas":0},{"hour":"02:00","spend":8363,"purchases":0,"val":0,"roas":0},{"hour":"03:00","spend":4761,"purchases":0,"val":0,"roas":0},{"hour":"04:00","spend":3886,"purchases":1,"val":64900,"roas":1670.0977869274318},{"hour":"05:00","spend":3891,"purchases":0,"val":0,"roas":0},{"hour":"06:00","spend":7971,"purchases":0,"val":0,"roas":0},{"hour":"07:00","spend":13240,"purchases":2,"val":150500,"roas":1136.7069486404835},{"hour":"08:00","spend":13988,"purchases":2,"val":205900,"roas":1471.9759794109236},{"hour":"09:00","spend":1654,"purchases":0,"val":0,"roas":0}],"01.통살(ASC)(하이브리드)_TCPA_A+SC캠페인_ALL_C7_수_표준기여_3028_260611":[{"hour":"00:00","spend":10548,"purchases":1,"val":96350,"roas":913.4433067880167},{"hour":"01:00","spend":6304,"purchases":1,"val":176000,"roas":2791.8781725888325},{"hour":"02:00","spend":4704,"purchases":0,"val":0,"roas":0},{"hour":"03:00","spend":2222,"purchases":0,"val":0,"roas":0},{"hour":"04:00","spend":1891,"purchases":0,"val":0,"roas":0},{"hour":"05:00","spend":2016,"purchases":0,"val":0,"roas":0},{"hour":"06:00","spend":4854,"purchases":0,"val":0,"roas":0},{"hour":"07:00","spend":5773,"purchases":0,"val":0,"roas":0},{"hour":"08:00","spend":7239,"purchases":1,"val":52900,"roas":730.7639176681862},{"hour":"09:00","spend":416,"purchases":0,"val":0,"roas":0}],"01.통살(ASC)(하이브리드)_A+SC캠페인_구매최적화_수_표준기여_3028_260611":[{"hour":"00:00","spend":5049,"purchases":0,"val":0,"roas":0},{"hour":"01:00","spend":1386,"purchases":0,"val":0,"roas":0},{"hour":"02:00","spend":998,"purchases":0,"val":0,"roas":0},{"hour":"03:00","spend":686,"purchases":0,"val":0,"roas":0},{"hour":"04:00","spend":242,"purchases":0,"val":0,"roas":0},{"hour":"05:00","spend":114,"purchases":0,"val":0,"roas":0},{"hour":"06:00","spend":589,"purchases":0,"val":0,"roas":0},{"hour":"07:00","spend":3375,"purchases":0,"val":0,"roas":0},{"hour":"08:00","spend":3458,"purchases":0,"val":0,"roas":0},{"hour":"09:00","spend":0,"purchases":0,"val":0,"roas":0}],"01.통살(ASC)(하이브리드)_TROAS_A+SC캠페인_구매최적화_값_표준기여_3028_260611":[{"hour":"00:00","spend":34350,"purchases":2,"val":106400,"roas":309.75254730713243},{"hour":"01:00","spend":19504,"purchases":0,"val":0,"roas":0},{"hour":"02:00","spend":12206,"purchases":0,"val":0,"roas":0},{"hour":"03:00","spend":9192,"purchases":0,"val":0,"roas":0},{"hour":"04:00","spend":4997,"purchases":0,"val":0,"roas":0},{"hour":"05:00","spend":9582,"purchases":2,"val":155650,"roas":1624.3999165101234},{"hour":"06:00","spend":13282,"purchases":0,"val":0,"roas":0},{"hour":"07:00","spend":19214,"purchases":0,"val":0,"roas":0},{"hour":"08:00","spend":15599,"purchases":0,"val":0,"roas":0},{"hour":"09:00","spend":1547,"purchases":0,"val":0,"roas":0}],"17.안심볶음밥(ASC)(메가딜)_TCPA_A+SC캠페인_ALL_C7_수_표준기여_2903_260705":[{"hour":"00:00","spend":9895,"purchases":1,"val":45900,"roas":463.8706417382516},{"hour":"01:00","spend":3259,"purchases":0,"val":0,"roas":0},{"hour":"02:00","spend":276,"purchases":0,"val":0,"roas":0},{"hour":"03:00","spend":731,"purchases":0,"val":0,"roas":0},{"hour":"04:00","spend":455,"purchases":0,"val":0,"roas":0},{"hour":"05:00","spend":585,"purchases":0,"val":0,"roas":0},{"hour":"06:00","spend":686,"purchases":0,"val":0,"roas":0},{"hour":"07:00","spend":1519,"purchases":0,"val":0,"roas":0},{"hour":"08:00","spend":620,"purchases":0,"val":0,"roas":0},{"hour":"09:00","spend":22,"purchases":0,"val":0,"roas":0}],"17.안심볶음밥(ASC)(메가딜)_TROAS_A+SC캠페인_구매최적화_값_표준기여_2903_260705":[{"hour":"00:00","spend":5975,"purchases":0,"val":0,"roas":0},{"hour":"01:00","spend":4514,"purchases":0,"val":0,"roas":0},{"hour":"02:00","spend":3704,"purchases":0,"val":0,"roas":0},{"hour":"03:00","spend":2824,"purchases":0,"val":0,"roas":0},{"hour":"04:00","spend":1464,"purchases":0,"val":0,"roas":0},{"hour":"05:00","spend":1708,"purchases":0,"val":0,"roas":0},{"hour":"06:00","spend":3043,"purchases":0,"val":0,"roas":0},{"hour":"07:00","spend":4992,"purchases":0,"val":0,"roas":0},{"hour":"08:00","spend":6090,"purchases":0,"val":0,"roas":0},{"hour":"09:00","spend":392,"purchases":0,"val":0,"roas":0}],"17.안심볶음밥(ASC)(메가딜)_A+SC캠페인_구매최적화_수_표준기여_2903_260705":[{"hour":"00:00","spend":5839,"purchases":0,"val":0,"roas":0},{"hour":"01:00","spend":2781,"purchases":1,"val":185800,"roas":6681.049982020856},{"hour":"02:00","spend":1612,"purchases":0,"val":0,"roas":0},{"hour":"03:00","spend":780,"purchases":0,"val":0,"roas":0},{"hour":"04:00","spend":1785,"purchases":0,"val":0,"roas":0},{"hour":"05:00","spend":523,"purchases":0,"val":0,"roas":0},{"hour":"06:00","spend":2174,"purchases":0,"val":0,"roas":0},{"hour":"07:00","spend":1923,"purchases":0,"val":0,"roas":0},{"hour":"08:00","spend":4404,"purchases":0,"val":0,"roas":0},{"hour":"09:00","spend":412,"purchases":0,"val":0,"roas":0}],"16.안심크리스피(ASC)(메가딜)_A+SC 캠페인_구매최적화_수_표준기여_2908_260621":[{"hour":"00:00","spend":7324,"purchases":0,"val":0,"roas":0},{"hour":"01:00","spend":3387,"purchases":0,"val":0,"roas":0},{"hour":"02:00","spend":1881,"purchases":0,"val":0,"roas":0},{"hour":"03:00","spend":1115,"purchases":0,"val":0,"roas":0},{"hour":"04:00","spend":769,"purchases":0,"val":0,"roas":0},{"hour":"05:00","spend":499,"purchases":0,"val":0,"roas":0},{"hour":"06:00","spend":1105,"purchases":0,"val":0,"roas":0},{"hour":"07:00","spend":968,"purchases":1,"val":44700,"roas":4617.768595041322},{"hour":"08:00","spend":2305,"purchases":0,"val":0,"roas":0},{"hour":"09:00","spend":223,"purchases":0,"val":0,"roas":0}],"16.안심크리스피(ASC)(메가딜)_TCPA_A+SC캠페인_ALL_C7_수_표준기여_2908_260621":[{"hour":"00:00","spend":4437,"purchases":1,"val":25900,"roas":583.7277439711517},{"hour":"01:00","spend":3069,"purchases":0,"val":0,"roas":0},{"hour":"02:00","spend":1719,"purchases":0,"val":0,"roas":0},{"hour":"03:00","spend":1062,"purchases":0,"val":0,"roas":0},{"hour":"04:00","spend":574,"purchases":0,"val":0,"roas":0},{"hour":"05:00","spend":1160,"purchases":1,"val":44000,"roas":3793.103448275862},{"hour":"06:00","spend":2511,"purchases":0,"val":0,"roas":0},{"hour":"07:00","spend":6712,"purchases":0,"val":0,"roas":0},{"hour":"08:00","spend":8959,"purchases":0,"val":0,"roas":0},{"hour":"09:00","spend":668,"purchases":0,"val":0,"roas":0}],"21.통살+그릴드(ASC)(메가딜)_TROAS_A+SC캠페인_구매최적화_값_표준기여_3068_260617":[{"hour":"00:00","spend":9785,"purchases":0,"val":0,"roas":0},{"hour":"01:00","spend":3285,"purchases":1,"val":59700,"roas":1817.351598173516},{"hour":"02:00","spend":2671,"purchases":0,"val":0,"roas":0},{"hour":"03:00","spend":2470,"purchases":0,"val":0,"roas":0},{"hour":"04:00","spend":2248,"purchases":0,"val":0,"roas":0},{"hour":"05:00","spend":2924,"purchases":0,"val":0,"roas":0},{"hour":"06:00","spend":2770,"purchases":0,"val":0,"roas":0},{"hour":"07:00","spend":8141,"purchases":0,"val":0,"roas":0},{"hour":"08:00","spend":6767,"purchases":0,"val":0,"roas":0}],"21.통살+그릴드(ASC)(메가딜)_TCPA_A+SC캠페인_ALL_C7_수_표준기여_3068_260617":[{"hour":"00:00","spend":5,"purchases":0,"val":0,"roas":0},{"hour":"01:00","spend":12,"purchases":0,"val":0,"roas":0},{"hour":"02:00","spend":73,"purchases":0,"val":0,"roas":0},{"hour":"03:00","spend":2,"purchases":0,"val":0,"roas":0},{"hour":"05:00","spend":8,"purchases":0,"val":0,"roas":0},{"hour":"06:00","spend":89,"purchases":0,"val":0,"roas":0},{"hour":"07:00","spend":168,"purchases":0,"val":0,"roas":0},{"hour":"08:00","spend":115,"purchases":0,"val":0,"roas":0}],"21.통살+그릴드(ASC)(메가딜)_A+SC캠페인_구매최적화_수_표준기여_3068_260617":[{"hour":"00:00","spend":9434,"purchases":0,"val":0,"roas":0},{"hour":"01:00","spend":6822,"purchases":0,"val":0,"roas":0},{"hour":"02:00","spend":5667,"purchases":0,"val":0,"roas":0},{"hour":"03:00","spend":4100,"purchases":1,"val":59700,"roas":1456.0975609756097},{"hour":"04:00","spend":1758,"purchases":1,"val":59700,"roas":3395.904436860068},{"hour":"05:00","spend":1888,"purchases":0,"val":0,"roas":0},{"hour":"06:00","spend":4583,"purchases":0,"val":0,"roas":0},{"hour":"07:00","spend":11788,"purchases":0,"val":0,"roas":0},{"hour":"08:00","spend":8575,"purchases":0,"val":0,"roas":0},{"hour":"09:00","spend":765,"purchases":0,"val":0,"roas":0}],"03.닭다리살(ASC)(1010)_A+SC캠페인_구매최적화_수_표준기여_2604_260618_유정":[{"hour":"00:00","spend":7623,"purchases":1,"val":54700,"roas":717.5652630198084},{"hour":"01:00","spend":3862,"purchases":0,"val":0,"roas":0},{"hour":"02:00","spend":1108,"purchases":0,"val":0,"roas":0},{"hour":"03:00","spend":869,"purchases":0,"val":0,"roas":0},{"hour":"04:00","spend":426,"purchases":0,"val":0,"roas":0},{"hour":"05:00","spend":1469,"purchases":0,"val":0,"roas":0},{"hour":"06:00","spend":3335,"purchases":0,"val":0,"roas":0},{"hour":"07:00","spend":5453,"purchases":0,"val":0,"roas":0},{"hour":"08:00","spend":4528,"purchases":0,"val":0,"roas":0},{"hour":"09:00","spend":367,"purchases":0,"val":0,"roas":0}],"03.닭다리살(ASC)(1010)_TCPA_A+SC캠페인_ALL_C7_수_표준기여_2604_260618_유정":[{"hour":"00:00","spend":140,"purchases":0,"val":0,"roas":0},{"hour":"05:00","spend":26,"purchases":0,"val":0,"roas":0},{"hour":"06:00","spend":397,"purchases":0,"val":0,"roas":0},{"hour":"08:00","spend":1162,"purchases":0,"val":0,"roas":0}],"18.크리스피닭다리(ASC)_A+SC 캠페인_구매최적화_수_표준기여_2910_260705":[{"hour":"00:00","spend":2889,"purchases":0,"val":0,"roas":0},{"hour":"01:00","spend":1469,"purchases":0,"val":0,"roas":0},{"hour":"02:00","spend":1972,"purchases":0,"val":0,"roas":0},{"hour":"03:00","spend":829,"purchases":0,"val":0,"roas":0},{"hour":"04:00","spend":514,"purchases":0,"val":0,"roas":0},{"hour":"05:00","spend":386,"purchases":0,"val":0,"roas":0},{"hour":"06:00","spend":556,"purchases":0,"val":0,"roas":0},{"hour":"07:00","spend":565,"purchases":0,"val":0,"roas":0},{"hour":"08:00","spend":610,"purchases":0,"val":0,"roas":0},{"hour":"09:00","spend":53,"purchases":0,"val":0,"roas":0}],"18.크리스피닭다리(ASC)_TCPA14000_A+SC 캠페인_ALL_C7_수_표준기여_2910_260705":[{"hour":"00:00","spend":2804,"purchases":0,"val":0,"roas":0},{"hour":"01:00","spend":3740,"purchases":0,"val":0,"roas":0},{"hour":"02:00","spend":2762,"purchases":0,"val":0,"roas":0},{"hour":"03:00","spend":1190,"purchases":0,"val":0,"roas":0},{"hour":"04:00","spend":1289,"purchases":0,"val":0,"roas":0},{"hour":"05:00","spend":1431,"purchases":0,"val":0,"roas":0},{"hour":"06:00","spend":1105,"purchases":0,"val":0,"roas":0},{"hour":"07:00","spend":1808,"purchases":0,"val":0,"roas":0},{"hour":"08:00","spend":2603,"purchases":0,"val":0,"roas":0},{"hour":"09:00","spend":215,"purchases":0,"val":0,"roas":0}],"07.크리스피(ASC)(메가딜)_A+SC캠페인_구매최적화_수_표준기여_2464_260628_유머니즘":[{"hour":"00:00","spend":1324,"purchases":0,"val":0,"roas":0},{"hour":"01:00","spend":1269,"purchases":0,"val":0,"roas":0},{"hour":"02:00","spend":1174,"purchases":1,"val":45400,"roas":3867.120954003407},{"hour":"03:00","spend":1751,"purchases":0,"val":0,"roas":0},{"hour":"04:00","spend":1256,"purchases":0,"val":0,"roas":0},{"hour":"05:00","spend":2154,"purchases":0,"val":0,"roas":0},{"hour":"06:00","spend":5471,"purchases":0,"val":0,"roas":0},{"hour":"07:00","spend":4312,"purchases":0,"val":0,"roas":0},{"hour":"08:00","spend":3021,"purchases":0,"val":0,"roas":0},{"hour":"09:00","spend":612,"purchases":0,"val":0,"roas":0}],"07.크리스피(ASC)(메가딜)_TROAS_A+SC캠페인_구매최적화_값_표준기여_2464_260628_유머니즘":[{"hour":"00:00","spend":3616,"purchases":0,"val":0,"roas":0},{"hour":"01:00","spend":1874,"purchases":0,"val":0,"roas":0},{"hour":"02:00","spend":1734,"purchases":0,"val":0,"roas":0},{"hour":"03:00","spend":994,"purchases":0,"val":0,"roas":0},{"hour":"04:00","spend":932,"purchases":0,"val":0,"roas":0},{"hour":"05:00","spend":1113,"purchases":0,"val":0,"roas":0},{"hour":"06:00","spend":1823,"purchases":0,"val":0,"roas":0},{"hour":"07:00","spend":6245,"purchases":0,"val":0,"roas":0},{"hour":"08:00","spend":4454,"purchases":0,"val":0,"roas":0},{"hour":"09:00","spend":64,"purchases":0,"val":0,"roas":0}],"07.크리스피(ASC)(메가딜)_TCPA_A+SC캠페인_ALL_C7_수_표준기여_2464_260628_유머니즘":[{"hour":"00:00","spend":5282,"purchases":0,"val":0,"roas":0},{"hour":"01:00","spend":2064,"purchases":0,"val":0,"roas":0},{"hour":"02:00","spend":1387,"purchases":0,"val":0,"roas":0},{"hour":"03:00","spend":1253,"purchases":0,"val":0,"roas":0},{"hour":"04:00","spend":687,"purchases":1,"val":43900,"roas":6390.101892285298},{"hour":"05:00","spend":873,"purchases":0,"val":0,"roas":0},{"hour":"06:00","spend":768,"purchases":0,"val":0,"roas":0},{"hour":"07:00","spend":1087,"purchases":0,"val":0,"roas":0},{"hour":"08:00","spend":1712,"purchases":0,"val":0,"roas":0},{"hour":"09:00","spend":181,"purchases":0,"val":0,"roas":0}],"07.크리스피(ASC)(101010)_A+SC 캠페인_구매최적화_수_표준기여_2659_02":[{"hour":"01:00","spend":0,"purchases":0,"val":0,"roas":0},{"hour":"02:00","spend":0,"purchases":0,"val":0,"roas":0},{"hour":"03:00","spend":0,"purchases":0,"val":0,"roas":0},{"hour":"04:00","spend":0,"purchases":0,"val":0,"roas":0},{"hour":"05:00","spend":0,"purchases":0,"val":0,"roas":0},{"hour":"06:00","spend":0,"purchases":0,"val":0,"roas":0},{"hour":"08:00","spend":0,"purchases":0,"val":0,"roas":0}],"07.크리스피(ASC)(101010)_TCPA14000_A+SC 캠페인_ALL_C7_수_표준기여_2659_260322":[{"hour":"01:00","spend":0,"purchases":0,"val":0,"roas":0},{"hour":"07:00","spend":0,"purchases":0,"val":0,"roas":0}]},"byProduct":[{"name":"크리스피닭가슴살","spend":2820565,"purchases":131,"val":7167386,"roas":254.111711660607},{"name":"김자반밥바","spend":1008937,"purchases":63,"val":3022692,"roas":299.5917485432688},{"name":"닭가슴살","spend":823209,"purchases":27,"val":1937400,"roas":235.34728118861676},{"name":"닭다리","spend":623037,"purchases":30,"val":1692200,"roas":271.60505716353924},{"name":"안심폭탄볶음밥","spend":405598,"purchases":17,"val":1334400,"roas":328.99570510702716},{"name":"크리스피안심","spend":317769,"purchases":13,"val":744100,"roas":234.1638108185506},{"name":"크리스피닭다리","spend":197331,"purchases":3,"val":166800,"roas":84.52802651382703},{"name":"통살+그릴드","spend":97606,"purchases":3,"val":179100,"roas":183.49281806446325}],"byCampaign":[{"name":"20.김자반밥바(ASC)(메가딜)_TROAS_A+SC캠페인_구매최적화_값_표준기여_3003_260527","spend":612110,"purchases":35,"val":1877492,"roas":306.72460832203365},{"name":"07.크리스피(ASC)(메가딜)_TCPA16000_A+SC 캠페인_ALL_수_표준기여_2464","spend":495794,"purchases":24,"val":1052150,"roas":212.21515387439135},{"name":"07.크리스피(ASC)(메가딜)_A+SC 캠페인_구매최적화_수_표준기여_2464","spend":369791,"purchases":17,"val":837850,"roas":226.57392959807027},{"name":"07.크리스피(ASC)(1010)_TROAS_A+SC캠페인_구매최적화_값_표준기여_2992_260527","spend":339909,"purchases":15,"val":835900,"roas":245.91876060945722},{"name":"07.크리스피(ASC)(메가딜)_A+SC 캠페인_구매최적화_수_표준기여_2464_260404","spend":294639,"purchases":14,"val":634300,"roas":215.28039397364233},{"name":"03.닭다리살(ASC)(1010)_A+SC캠페인_구매최적화_수_표준기여_2604_260519","spend":279290,"purchases":15,"val":785600,"roas":281.2846861684987},{"name":"07.크리스피(ASC)(메가딜)_A+SC 캠페인_구매최적화_수_표준기여_2464_260404_test","spend":271021,"purchases":16,"val":653450,"roas":241.1067777035728},{"name":"07.크리스피(ASC)(메가딜)_A+SC 캠페인_구매최적화_수_표준기여_2464_260416_intern","spend":259943,"purchases":18,"val":1079100,"roas":415.12947069165165},{"name":"07.크리스피(ASC)(메가딜)_TCPA14000_A+SC 캠페인_ALL_C7_수_표준기여_2464_260416_intern","spend":236886,"purchases":8,"val":667536,"roas":281.79630708442033},{"name":"20.김자반밥(ASC)(메가딜)_TCPA_A+SC캠페인_ALL_C7_수_표준기여_3003_260527","spend":226855,"purchases":16,"val":698300,"roas":307.8177690595314},{"name":"16.안심크리스피(ASC)(메가딜)_TCPA14000_A+SC 캠페인_ALL_C7_수_표준기여_2863_260327","spend":226596,"purchases":10,"val":629500,"roas":277.8071987148935},{"name":"01.통살(ASC)(101010)_TCPA16000_A+SC 캠페인_ALL_V1C7_수_표준기여_2336","spend":199653,"purchases":11,"val":680500,"roas":340.8413597591822},{"name":"07.크리스피(ASC)(통합)_A+SC 캠페인_구매최적화_수_표준기여_통합_260511","spend":191741,"purchases":7,"val":416150,"roas":217.03756630037395},{"name":"07.크리스피(ASC)(메가딜)_TCPA16000_A+SC 캠페인_ALL_수_표준기여_2464_260403","spend":188248,"purchases":8,"val":765250,"roas":406.5116229654499},{"name":"20.김자반밥바(ASC)(메가딜)_A+SC캠페인_구매최적화_수_표준기여_3003_260527","spend":147217,"purchases":10,"val":387300,"roas":263.08103004408457},{"name":"01.통살(ASC)(메가딜)_TCPA20000_A+SC 캠페인_ALL_V1C7_수_표준기여_1874","spend":141272,"purchases":3,"val":188600,"roas":133.50133076618155},{"name":"01.통살(ASC)(하이브리드)_TROAS_A+SC캠페인_구매최적화_값_표준기여_3028_260611","spend":139473,"purchases":4,"val":262050,"roas":187.88582736443612},{"name":"03.닭다리살(ASC)(101010)_A+SC 캠페인_구매최적화_수_표준기여_2358_260410_intern","spend":135996,"purchases":3,"val":200500,"roas":147.43080678843498},{"name":"01.통살(ASC)(101010)_A+SC 캠페인_ALL_V1C7_수_표준기여_2336_AI","spend":134782,"purchases":1,"val":182300,"roas":135.25544954073987},{"name":"03.닭다리살(ASC)(1010)_TROAS_A+SC캠페인_구매최적화_값_표준기여_2604_260519","spend":123727,"purchases":7,"val":394700,"roas":319.0087854712391},{"name":"17.안심볶음밥(ASC)(메가딜)_TCPA_A+SC 캠페인_ALL_C7_수_표준기여_2903_260409","spend":107448,"purchases":2,"val":197400,"roas":183.71677462586553},{"name":"17.안심볶음밥(ASC)(메가딜)_A+SC 캠페인_구매최적화_수_표준기여_2903_260507_남자","spend":107299,"purchases":6,"val":298000,"roas":277.7285902012134},{"name":"17.안심볶음밥(ASC)(메가딜)_A+SC 캠페인_구매최적화_수_표준기여_2903_260609_남자(가치조정)","spend":95077,"purchases":7,"val":607300,"roas":638.7454379082217},{"name":"18.크리스피닭다리(ASC)_TROAS_A+SC 캠페인_구매최적화_값_표준기여_2910_260518","spend":74402,"purchases":1,"val":42000,"roas":56.450095427542266},{"name":"01.통살(ASC)(101010)_TCPA16000_A+SC 캠페인_ALL_V1C7_수_표준기여_2336_03","spend":68703,"purchases":4,"val":238900,"roas":347.72862902638894},{"name":"21.통살+그릴드(ASC)(메가딜)_A+SC캠페인_구매최적화_수_표준기여_3068_260617","spend":56045,"purchases":2,"val":119400,"roas":213.04309037380676},{"name":"07.크리스피(ASC)(101010)_A+SC 캠페인_구매최적화_수_표준기여_2659_260322","spend":47573,"purchases":1,"val":66000,"roas":138.73415592878314},{"name":"01.통살(ASC)(하이브리드)_TCPA_A+SC캠페인_ALL_C7_수_표준기여_3028_260611","spend":46252,"purchases":3,"val":325250,"roas":703.2128340396091},{"name":"21.통살+그릴드(ASC)(메가딜)_TROAS_A+SC캠페인_구매최적화_값_표준기여_3068_260617","spend":41089,"purchases":1,"val":59700,"roas":145.2943610211979},{"name":"16.안심크리스피(ASC)(메가딜)_TROAS_A+SC 캠페인_구매최적화_값_표준기여_2908_260518","spend":40324,"purchases":0,"val":0,"roas":0},{"name":"03.닭다리살(ASC)(1010)_TCPA_A+SC캠페인_ALL_C7_수_표준기여_2604_260519","spend":36420,"purchases":2,"val":112200,"roas":308.0724876441516},{"name":"17.안심볶음밥(ASC)(메가딜)_TROAS_A+SC캠페인_구매최적화_값_표준기여_2903_260705","spend":34829,"purchases":0,"val":0,"roas":0},{"name":"18.크리스피닭다리(ASC)_TCPA14000_A+SC 캠페인_ALL_C7_수_표준기여_2910_260416","spend":33512,"purchases":1,"val":54900,"roas":163.8219145380759},{"name":"18.크리스피닭다리(ASC)_TCPA14000_A+SC 캠페인_ALL_C7_수_표준기여_2910_260525","spend":33423,"purchases":0,"val":0,"roas":0},{"name":"16.안심크리스피(ASC)(메가딜)_TCPA_A+SC캠페인_ALL_C7_수_표준기여_2908_260621","spend":31169,"purchases":2,"val":69900,"roas":224.26128525137153},{"name":"07.크리스피(ASC)(101010)_TCPA14000_A+SC 캠페인_ALL_C7_수_표준기여_2659_260424_intern","spend":29753,"purchases":0,"val":0,"roas":0},{"name":"01.통살(ASC)(101010)_TCPA_A+SC 캠페인_ALL_C7_수_표준기여_2336_260410_intern","spend":29164,"purchases":1,"val":59800,"roas":205.0473186119874},{"name":"03.닭다리살(ASC)(1010)_A+SC캠페인_구매최적화_수_표준기여_2604_260618_유정","spend":29002,"purchases":1,"val":54700,"roas":188.60768222881183},{"name":"07.크리스피(ASC)(1010)_A+SC캠페인_구매최적화_수_표준기여_2992_260527","spend":26356,"purchases":1,"val":70400,"roas":267.1118530884808},{"name":"01.통살(ASC)(101010)_A+SC 캠페인_구매최적화_수_표준기여_2336_260410_intern","spend":25868,"purchases":0,"val":0,"roas":0},{"name":"07.크리스피(ASC)(메가딜)_TROAS_A+SC캠페인_구매최적화_값_표준기여_2464_260628_유머니즘","spend":22849,"purchases":0,"val":0,"roas":0},{"name":"20.김자반밥바(ASC)(메가딜)_A+SC캠페인_구매최적화_수_표준기여_3003_260603","spend":22755,"purchases":2,"val":59600,"roas":261.92045704240826},{"name":"07.크리스피(ASC)(메가딜)_A+SC캠페인_구매최적화_수_표준기여_2464_260628_유머니즘","spend":22632,"purchases":1,"val":45400,"roas":200.6009190526688},{"name":"17.안심볶음밥(ASC)(메가딜)_A+SC캠페인_구매최적화_수_표준기여_2903_260705","spend":22344,"purchases":1,"val":185800,"roas":831.5431435732188},{"name":"01.통살(ASC)(101010)_TCPA16000_A+SC 캠페인_ALL_V1C7_수_표준기여_2336_02","spend":22136,"purchases":0,"val":0,"roas":0},{"name":"17.안심볶음밥(ASC)(메가딜)_A+SC 캠페인_구매최적화_수_표준기여_2903_260507_남자_02","spend":20553,"purchases":0,"val":0,"roas":0},{"name":"16.안심크리스피(ASC)(메가딜)_A+SC 캠페인_구매최적화_수_표준기여_2908_260621","spend":19680,"purchases":1,"val":44700,"roas":227.13414634146343},{"name":"18.크리스피닭다리(ASC)_TCPA14000_A+SC 캠페인_ALL_C7_수_표준기여_2910_260705","spend":18947,"purchases":0,"val":0,"roas":0},{"name":"17.안심볶음밥(ASC)(메가딜)_TCPA_A+SC캠페인_ALL_C7_수_표준기여_2903_260705","spend":18048,"purchases":1,"val":45900,"roas":254.32180851063828},{"name":"03.닭다리살(ASC)(101010)_A+SC 캠페인_구매최적화_값_표준기여_2358","spend":16877,"purchases":2,"val":144500,"roas":856.1948213545062},{"name":"01.통살(ASC)(하이브리드)_A+SC캠페인_구매최적화_수_표준기여_3028_260611","spend":15906,"purchases":0,"val":0,"roas":0},{"name":"07.크리스피(ASC)(메가딜)_TCPA_A+SC캠페인_ALL_C7_수_표준기여_2464_260628_유머니즘","spend":15358,"purchases":1,"val":43900,"roas":285.844511004037},{"name":"18.크리스피닭다리(ASC)_A+SC 캠페인_구매최적화_수_표준기여_2910_260416_intern(광고소진후종료)","spend":14694,"purchases":1,"val":69900,"roas":475.7043691302573},{"name":"18.크리스피닭다리(ASC)_A+SC 캠페인_구매최적화_수_표준기여_2910_260416","spend":12489,"purchases":0,"val":0,"roas":0},{"name":"18.크리스피닭다리(ASC)_A+SC 캠페인_구매최적화_수_표준기여_2910_260705","spend":9864,"purchases":0,"val":0,"roas":0},{"name":"07.크리스피(ASC)(1010)_TCPA_A+SC캠페인_ALL_C7_수_표준기여_2992_260705","spend":8072,"purchases":0,"val":0,"roas":0},{"name":"03.닭다리살(ASC)(1010)_TCPA_A+SC캠페인_ALL_C7_수_표준기여_2604_260618_유정","spend":1725,"purchases":0,"val":0,"roas":0},{"name":"21.통살+그릴드(ASC)(메가딜)_TCPA_A+SC캠페인_ALL_C7_수_표준기여_3068_260617","spend":472,"purchases":0,"val":0,"roas":0},{"name":"07.크리스피(ASC)(101010)_A+SC 캠페인_구매최적화_수_표준기여_2659_02","spend":0,"purchases":0,"val":0,"roas":0},{"name":"16.안심크리스피(ASC)(메가딜)_A+SC 캠페인_구매최적화_수_표준기여_2863_260327","spend":0,"purchases":0,"val":0,"roas":0},{"name":"07.크리스피(ASC)(101010)_TCPA14000_A+SC 캠페인_ALL_C7_수_표준기여_2659_260322","spend":0,"purchases":0,"val":0,"roas":0}],"byAd":[{"name":"260531_HKBB_FB_new_all_김자반밥바네고_가격_세트가격_릴스_prod_3003_ahi_og","product":"김자반밥바","person":"안혜인","camp":"20.김자반밥바(ASC)(메가딜)_A+SC캠페인_구매최적화_수_표준기여_3003_260527","spend":514756,"purchases":32,"val":1725292,"roas":335.1669528864161},{"name":"260607_HCP_FB_new_all_이가격_가격_제품력_릴스_prod_2464_chy_og","product":"크리스피닭가슴살","person":"천혜영","camp":"07.크리스피(ASC)(메가딜)_A+SC 캠페인_구매최적화_수_표준기여_2464_260416_intern","spend":419400,"purchases":26,"val":1844350,"roas":439.759179780639},{"name":"260419_HCP_FB_new_all_안사길잘했다_가격_할인율_릴스_prod_2464_ahi_og","product":"크리스피닭가슴살","person":"안혜인","camp":"07.크리스피(ASC)(메가딜)_A+SC 캠페인_구매최적화_수_표준기여_2464","spend":356745,"purchases":15,"val":726850,"roas":203.74497189869513},{"name":"260403_HCP_FB_new_all_벌써끝나갑니다A_가격_개당가격_이미지_prod_2464_ahi_og - 사본","product":"크리스피닭가슴살","person":"안혜인","camp":"07.크리스피(ASC)(메가딜)_TCPA16000_A+SC 캠페인_ALL_수_표준기여_2464","spend":350052,"purchases":19,"val":812850,"roas":232.20835761543998},{"name":"260409_HCP_FB_new_all_마케터네고2_가격_개당가격_릴스_prod_2464_ahi_og - 사본","product":"크리스피닭가슴살","person":"안혜인","camp":"07.크리스피(ASC)(메가딜)_A+SC 캠페인_구매최적화_수_표준기여_2464_260404_test","spend":271021,"purchases":16,"val":653450,"roas":241.1067777035728},{"name":"***260419_HCP_FB_new_all_현시점가장_제품력_맛_릴스_prod_2464_ahi_og - 사본","product":"크리스피닭가슴살","person":"안혜인","camp":"07.크리스피(ASC)(메가딜)_A+SC 캠페인_구매최적화_수_표준기여_2464_260404","spend":260311,"purchases":13,"val":608500,"roas":233.75884999097232},{"name":"260503_HCP_FB_new_all_진짜요?_가격_제품력_릴스_prod_2659_chy_og","product":"크리스피닭가슴살","person":"천혜영","camp":"07.크리스피(ASC)(메가딜)_TCPA14000_A+SC 캠페인_ALL_C7_수_표준기여_2464_260416_intern","spend":236465,"purchases":8,"val":667536,"roas":282.2980145053179},{"name":"260426_HCPT_FB_new_all_CS네고_페르소나_가격_릴스_prod_2908_ksr_og - 사본","product":"크리스피안심","person":"김승룡","camp":"16.안심크리스피(ASC)(메가딜)_TCPA14000_A+SC 캠페인_ALL_C7_수_표준기여_2863_260327","spend":226596,"purchases":10,"val":629500,"roas":277.8071987148935},{"name":"260607_HSL_FB_new_all_이거진짜위험_제품력_성분_릴스_prod_2996_ahi_og","product":"닭다리","person":"안혜인","camp":"03.닭다리살(ASC)(1010)_A+SC캠페인_구매최적화_수_표준기여_2604_260519","spend":224931,"purchases":12,"val":622500,"roas":276.7515371380557},{"name":"260531_HCP_FB_new_all_큰일_제품력_가격_릴스_prod_2992_jhr_og","product":"크리스피닭가슴살","person":"정혜림","camp":"07.크리스피(ASC)(1010)_TROAS_A+SC캠페인_구매최적화_값_표준기여_2992_260527","spend":219445,"purchases":13,"val":753900,"roas":343.5484973455763},{"name":"260531_HKBB_FB_new_all_30분더자_제품력_릴스_prod_3003_psh_og","product":"김자반밥바","person":"박시현","camp":"20.김자반밥바(ASC)(메가딜)_A+SC캠페인_구매최적화_수_표준기여_3003_260527","spend":188041,"purchases":11,"val":441900,"roas":235.00194106604414},{"name":"260111_HDG_FB_new_all_언니들_가격_영양성분_릴스_prod_2336_ljh_og","product":"닭가슴살","person":"이지현","camp":"01.통살(ASC)(101010)_TCPA16000_A+SC 캠페인_ALL_V1C7_수_표준기여_2336","spend":183213,"purchases":11,"val":680500,"roas":371.42560844481557},{"name":"260531_HKBB_FB_new_all_맛의끝판왕_맛_제품력_릴스_prod_3003_psh_og","product":"김자반밥바","person":"박시현","camp":"20.김자반밥바(ASC)(메가딜)_A+SC캠페인_구매최적화_수_표준기여_3003_260527","spend":173166,"purchases":14,"val":595300,"roas":343.77418199877576},{"name":"260403_HCP_FB_new_all_쌀때쟁이세요A_가격_할인율_이미지_prod_2464_ahi_og - 사본","product":"크리스피닭가슴살","person":"안혜인","camp":"07.크리스피(ASC)(메가딜)_TCPA16000_A+SC 캠페인_ALL_수_표준기여_2464","spend":145742,"purchases":5,"val":239300,"roas":164.1942610915179},{"name":"260614_HDG_FB_new_all_6월여기다_제품력_구성_릴스_prod_3028_ljh_og","product":"닭가슴살","person":"이지현","camp":"01.통살(ASC)(하이브리드)_TROAS_A+SC캠페인_구매최적화_값_표준기여_3028_260611","spend":138064,"purchases":4,"val":262050,"roas":189.80327963842856},{"name":"260614_HSL_FB_new_all_벌써샀어_가격_제품력_릴스_prod_2358_jjy_og","product":"닭다리","person":"장지영","camp":"03.닭다리살(ASC)(101010)_A+SC 캠페인_구매최적화_수_표준기여_2358_260410_intern","spend":131993,"purchases":3,"val":200500,"roas":151.90199480275467},{"name":"260614_HKBB_FB_new_all_한끼통살에_가격_맛_릴스_prod_3003_psh_og","product":"김자반밥바","person":"박시현","camp":"20.김자반밥(ASC)(메가딜)_TCPA_A+SC캠페인_ALL_C7_수_표준기여_3003_260527","spend":130260,"purchases":6,"val":260200,"roas":199.75433747888837},{"name":"260503_HCP_FB_new_all_어제사신분죄송_가격_할인율_이미지_prod_2464_ahi_og","product":"크리스피닭가슴살","person":"안혜인","camp":"07.크리스피(ASC)(메가딜)_A+SC 캠페인_구매최적화_수_표준기여_2464","spend":123524,"purchases":8,"val":485500,"roas":393.04102846410416},{"name":"260531_HSL_FB_new_all_먹어본식단템중에_제품력_맛_릴스_prod_2996_ahi_og","product":"닭다리","person":"안혜인","camp":"03.닭다리살(ASC)(1010)_TROAS_A+SC캠페인_구매최적화_값_표준기여_2604_260519","spend":122775,"purchases":7,"val":394700,"roas":321.4823864793321},{"name":"260614_HTR_FB_new_all_5분컷_가격_제품력_릴스_prod_2903_bye_og","product":"안심폭탄볶음밥","person":"배영언","camp":"17.안심볶음밥(ASC)(메가딜)_A+SC 캠페인_구매최적화_수_표준기여_2903_260507_남자","spend":107299,"purchases":6,"val":298000,"roas":277.7285902012134},{"name":"260614_HCP_FB_new_all_찾았어요제품력_제품력_가격_릴스_prod_2992_chy_og","product":"크리스피닭가슴살","person":"천혜영","camp":"07.크리스피(ASC)(1010)_TROAS_A+SC캠페인_구매최적화_값_표준기여_2992_260527","spend":102503,"purchases":1,"val":41000,"roas":39.998829302557},{"name":"260510_HTR_FB_new_all_계산좀해주세요_가격_제품력_릴스_prod_2903_bye_og","product":"안심폭탄볶음밥","person":"배영언","camp":"17.안심볶음밥(ASC)(메가딜)_TCPA_A+SC 캠페인_ALL_C7_수_표준기여_2903_260409","spend":102384,"purchases":2,"val":197400,"roas":192.80356305672763},{"name":"260427_HDG_FB_new_all_할인에목숨걺1_가격_할인율_릴스_prod_2336_bye_ai_h_","product":"닭가슴살","person":"담당자 미확인","camp":"01.통살(ASC)(101010)_A+SC 캠페인_ALL_V1C7_수_표준기여_2336_AI","spend":102196,"purchases":0,"val":0,"roas":0},{"name":"251221_HDG_FB_new_all_주문오류_어그로_가격_릴스_prod_1874_ljh_og - 사본 - 사본","product":"닭가슴살","person":"이지현","camp":"01.통살(ASC)(메가딜)_TCPA20000_A+SC 캠페인_ALL_V1C7_수_표준기여_1874","spend":95749,"purchases":0,"val":0,"roas":0},{"name":"260628_HTG_FB_new_all_쇼핑꿀팁_가격_제품력_릴스_prod_3068_ysy_og","product":"통살+그릴드","person":"양서영","camp":"21.통살+그릴드(ASC)(메가딜)_A+SC캠페인_구매최적화_수_표준기여_3068_260617","spend":84040,"purchases":1,"val":59700,"roas":71.03760114231319},{"name":"260517_HTR_FB_new_all_할인해주세요_가격_제품력_릴스_prod_2903_bye_og","product":"안심폭탄볶음밥","person":"배영언","camp":"17.안심볶음밥(ASC)(메가딜)_A+SC 캠페인_구매최적화_수_표준기여_2903_260609_남자(가치조정)","spend":69009,"purchases":4,"val":363800,"roas":527.1776145140489},{"name":"260419_HDG_FB_new_all_식단챌_맛_제품력_릴스_prod_2336_ljh_og - 사본","product":"닭가슴살","person":"이지현","camp":"01.통살(ASC)(101010)_TCPA16000_A+SC 캠페인_ALL_V1C7_수_표준기여_2336_03","spend":68664,"purchases":4,"val":238900,"roas":347.9261330537108},{"name":"260607_HCPL_FB_new_all_개큰오해_리스티클_제품력_릴스_prod_2910_ksr_og","product":"크리스피닭다리","person":"김승룡","camp":"18.크리스피닭다리(ASC)_A+SC 캠페인_구매최적화_수_표준기여_2910_260416","spend":63247,"purchases":1,"val":42000,"roas":66.4063117618227},{"name":"260621_HTR_FB_new_all_이거미쳤습니다_제품력_가격_릴스_prod_2903_bye_og","product":"안심폭탄볶음밥","person":"배영언","camp":"17.안심볶음밥(ASC)(메가딜)_A+SC캠페인_구매최적화_수_표준기여_2903_260705","spend":56382,"purchases":1,"val":185800,"roas":329.5377957504168},{"name":"260607_HSL_FB_new_all_나가주세요_제품력_맛_릴스_prod_2996_ahi_og","product":"닭다리","person":"안혜인","camp":"03.닭다리살(ASC)(1010)_A+SC캠페인_구매최적화_수_표준기여_2604_260519","spend":55311,"purchases":3,"val":163100,"roas":294.878053190143},{"name":"260426_HCP_FB_new_all_친오빠네고2_가격_할인율_릴스_prod_2659_ahi_og","product":"크리스피닭가슴살","person":"안혜인","camp":"07.크리스피(ASC)(101010)_A+SC 캠페인_구매최적화_수_표준기여_2659_260322","spend":47573,"purchases":1,"val":66000,"roas":138.73415592878314},{"name":"260405_HDG_FB_new_all_고물가뚫은_가격_어전시_릴스_prod_1874_ljh_og - 사본","product":"닭가슴살","person":"이지현","camp":"01.통살(ASC)(메가딜)_TCPA20000_A+SC 캠페인_ALL_V1C7_수_표준기여_1874","spend":45523,"purchases":3,"val":188600,"roas":414.2960701184017},{"name":"260503_HCP_FB_new_all_다시는없어요_가격_개당가격_이미지_prod_2464_ahi_og","product":"크리스피닭가슴살","person":"안혜인","camp":"07.크리스피(ASC)(메가딜)_A+SC 캠페인_구매최적화_수_표준기여_2464","spend":45464,"purchases":1,"val":41650,"roas":91.61094492345592},{"name":"260614_HDG_FB_new_all_큰일났다_구성_맛_릴스_prod_3028_ljh_og","product":"닭가슴살","person":"이지현","camp":"01.통살(ASC)(하이브리드)_TROAS_A+SC캠페인_구매최적화_값_표준기여_3028_260611","spend":44257,"purchases":3,"val":325250,"roas":734.9119913234065},{"name":"260614_HCPT_FB_new_all_속세맛으로_제품력_맛_릴스_prod_2908_ysy_og","product":"크리스피안심","person":"양서영","camp":"16.안심크리스피(ASC)(메가딜)_TROAS_A+SC 캠페인_구매최적화_값_표준기여_2908_260518","spend":37272,"purchases":0,"val":0,"roas":0},{"name":"260524_HSL_FB_new_all_특가구성닭다리_가격_구성_릴스_prod_2996_ahi_og","product":"닭다리","person":"안혜인","camp":"03.닭다리살(ASC)(1010)_TCPA_A+SC캠페인_ALL_C7_수_표준기여_2604_260519","spend":36420,"purchases":2,"val":112200,"roas":308.0724876441516},{"name":"260403_HCP_FB_new_all_먹방2분할가격_제품력_맛_릴스_prod_2464_ahi_og","product":"크리스피닭가슴살","person":"안혜인","camp":"07.크리스피(ASC)(메가딜)_A+SC 캠페인_구매최적화_수_표준기여_2464_260404","spend":34328,"purchases":1,"val":25800,"roas":75.15730598927989},{"name":"260607_HCPL_FB_new_all_식단되는_제품력_맛_릴스_prod_2910_ksr_og","product":"크리스피닭다리","person":"김승룡","camp":"18.크리스피닭다리(ASC)_TCPA14000_A+SC 캠페인_ALL_C7_수_표준기여_2910_260525","spend":33383,"purchases":0,"val":0,"roas":0},{"name":"260621_HCPT_FB_new_all_아가리어터_제품력_맛_릴스_prod_2908_ysy_og","product":"크리스피안심","person":"양서영","camp":"16.안심크리스피(ASC)(메가딜)_A+SC 캠페인_구매최적화_수_표준기여_2908_260621","spend":30674,"purchases":1,"val":44700,"roas":145.72602203820827},{"name":"260517_HCPL_FB_new_all_그냥드셔도됩니다_제품력_맛_릴스_prod_2910_ysy_og","product":"크리스피닭다리","person":"양서영","camp":"18.크리스피닭다리(ASC)_TCPA14000_A+SC 캠페인_ALL_C7_수_표준기여_2910_260416","spend":30405,"purchases":1,"val":54900,"roas":180.56240749876665},{"name":"260614_HCP_FB_new_all_언니들_맛_가격_릴스_prod_2992_chy_og","product":"크리스피닭가슴살","person":"천혜영","camp":"07.크리스피(ASC)(1010)_TROAS_A+SC캠페인_구매최적화_값_표준기여_2992_260527","spend":29091,"purchases":1,"val":70400,"roas":241.99924375236327},{"name":"260621_HCPL_FB_new_all_죄책감_혜택_제품력_릴스_prod_3069_ksr_og","product":"크리스피닭다리","person":"김승룡","camp":"18.크리스피닭다리(ASC)_A+SC 캠페인_구매최적화_수_표준기여_2910_260705","spend":28707,"purchases":0,"val":0,"roas":0},{"name":"260427_HDG_FB_new_all_할인에목숨걺2_가격_할인율_릴스_prod_2336_bye_ai_h_","product":"닭가슴살","person":"담당자 미확인","camp":"01.통살(ASC)(101010)_A+SC 캠페인_ALL_V1C7_수_표준기여_2336_AI","spend":24991,"purchases":1,"val":182300,"roas":729.4626065383537},{"name":"260614_HTR_FB_new_all_사먹지마세요_제품력_맛_릴스_prod_2903_bye_og","product":"안심폭탄볶음밥","person":"배영언","camp":"17.안심볶음밥(ASC)(메가딜)_A+SC 캠페인_구매최적화_수_표준기여_2903_260609_남자(가치조정)","spend":24188,"purchases":3,"val":243500,"roas":1006.6975359682488},{"name":"260607_HCP_FB_new_all_개손해봤어요_제품력_가격_릴스_prod_2659_ksg_og","product":"크리스피닭가슴살","person":"김선길","camp":"07.크리스피(ASC)(101010)_TCPA14000_A+SC 캠페인_ALL_C7_수_표준기여_2659_260424_intern","spend":23857,"purchases":0,"val":0,"roas":0},{"name":"260628_HCP_FB_new_all_유머니즘B_가격_개당가격_릴스_prod_2464_ahi_og - 사본","product":"크리스피닭가슴살","person":"안혜인","camp":"07.크리스피(ASC)(메가딜)_TROAS_A+SC캠페인_구매최적화_값_표준기여_2464_260628_유머니즘","spend":22849,"purchases":0,"val":0,"roas":0},{"name":"260628_HCP_FB_new_all_유머니즘B_가격_개당가격_릴스_prod_2464_ahi_og","product":"크리스피닭가슴살","person":"안혜인","camp":"07.크리스피(ASC)(메가딜)_A+SC캠페인_구매최적화_수_표준기여_2464_260628_유머니즘","spend":22632,"purchases":1,"val":45400,"roas":200.6009190526688},{"name":"260405_HDG_FB_new_all_통살골라_가격_맛_릴스_prod_2336_ljh_og - 사본","product":"닭가슴살","person":"이지현","camp":"01.통살(ASC)(101010)_TCPA16000_A+SC 캠페인_ALL_V1C7_수_표준기여_2336_02","spend":22108,"purchases":0,"val":0,"roas":0},{"name":"260531_HCP_FB_new_all_이거아직모르죠?_맛_제품력_릴스_prod_2464_chy_og","product":"크리스피닭가슴살","person":"천혜영","camp":"07.크리스피(ASC)(메가딜)_TCPA16000_A+SC 캠페인_ALL_수_표준기여_2464_260403","spend":21342,"purchases":0,"val":0,"roas":0},{"name":"260510_HTR_FB_new_all_솔직리뷰_제품력_맛_릴스_prod_2903_ksg_og","product":"안심폭탄볶음밥","person":"김선길","camp":"17.안심볶음밥(ASC)(메가딜)_A+SC 캠페인_구매최적화_수_표준기여_2903_260507_남자_02","spend":20426,"purchases":0,"val":0,"roas":0},{"name":"260621_HCPT_FB_new_all_밀가루부담적은제품_제품력_맛_릴스_prod_2908_ysy_og","product":"크리스피안심","person":"양서영","camp":"16.안심크리스피(ASC)(메가딜)_A+SC 캠페인_구매최적화_수_표준기여_2908_260621","spend":19983,"purchases":2,"val":69900,"roas":349.79732772856926},{"name":"260403_HCP_FB_new_all_벌써끝나갑니다A_가격_개당가격_이미지_prod_2464_ahi_og","product":"크리스피닭가슴살","person":"안혜인","camp":"07.크리스피(ASC)(통합)_A+SC 캠페인_구매최적화_수_표준기여_통합_260511","spend":18290,"purchases":0,"val":0,"roas":0},{"name":"260607_HDG_FB_new_all_입터짐방지_맛_제품력_릴스_prod_2336_kjy_og","product":"닭가슴살","person":"강주이","camp":"01.통살(ASC)(101010)_A+SC 캠페인_구매최적화_수_표준기여_2336_260410_intern","spend":17966,"purchases":0,"val":0,"roas":0},{"name":"260419_HDG_FB_new_all_식단챌_맛_제품력_릴스_prod_2336_ljh_og","product":"닭가슴살","person":"이지현","camp":"01.통살(ASC)(101010)_TCPA16000_A+SC 캠페인_ALL_V1C7_수_표준기여_2336","spend":16349,"purchases":0,"val":0,"roas":0},{"name":"260614_HSL_FB_new_all_싼데_맛_가격_릴스_prod_2358_jjy_og","product":"닭다리","person":"장지영","camp":"03.닭다리살(ASC)(101010)_A+SC 캠페인_구매최적화_값_표준기여_2358","spend":15680,"purchases":2,"val":144500,"roas":921.5561224489796},{"name":"260607_HDG_FB_new_all_역대급딜_가격_릴스_prod_2336_kjy_og","product":"닭가슴살","person":"강주이","camp":"01.통살(ASC)(101010)_A+SC 캠페인_구매최적화_수_표준기여_2336_260410_intern","spend":15360,"purchases":0,"val":0,"roas":0},{"name":"260628_HCP_FB_new_all_유머니즘A_가격_개당가격_릴스_prod_2464_ahi_og","product":"크리스피닭가슴살","person":"안혜인","camp":"07.크리스피(ASC)(메가딜)_A+SC캠페인_구매최적화_수_표준기여_2464_260628_유머니즘","spend":15358,"purchases":1,"val":43900,"roas":285.844511004037},{"name":"260621_HSL_FB_new_all_유정띠배너A_제품력_영양성분_릴스_prod_2996_ahi_og","product":"닭다리","person":"안혜인","camp":"03.닭다리살(ASC)(1010)_A+SC캠페인_구매최적화_수_표준기여_2604_260618_유정","spend":13816,"purchases":0,"val":0,"roas":0},{"name":"260531_HCPL_FB_new_all_승룡네고_가격_맛_릴스_prod_2910_ksr_og","product":"크리스피닭다리","person":"김승룡","camp":"18.크리스피닭다리(ASC)_TCPA14000_A+SC 캠페인_ALL_C7_수_표준기여_2910_260525","spend":13003,"purchases":1,"val":69900,"roas":537.5682534799662},{"name":"260614_HDG_FB_new_all_댕많아_구성_맛_릴스_prod_3028_ljh_og","product":"닭가슴살","person":"이지현","camp":"01.통살(ASC)(하이브리드)_A+SC캠페인_구매최적화_수_표준기여_3028_260611","spend":12411,"purchases":0,"val":0,"roas":0},{"name":"260621_HCPL_FB_new_all_죄책감_혜택_제품력_릴스_prod_2910_ksr_og","product":"크리스피닭다리","person":"김승룡","camp":"18.크리스피닭다리(ASC)_TROAS_A+SC 캠페인_구매최적화_값_표준기여_2910_260518","spend":10544,"purchases":0,"val":0,"roas":0},{"name":"260614_HDG_FB_new_all_받았어요_맛_제품력_릴스_prod_2336_kjy_og","product":"닭가슴살","person":"강주이","camp":"01.통살(ASC)(101010)_TCPA_A+SC 캠페인_ALL_C7_수_표준기여_2336_260410_intern","spend":10492,"purchases":1,"val":59800,"roas":569.9580632863134},{"name":"260621_HCP_FB_new_all_식단한다면서_제품력_가격_릴스_prod_2992_chy_og","product":"크리스피닭가슴살","person":"천혜영","camp":"07.크리스피(ASC)(1010)_TROAS_A+SC캠페인_구매최적화_값_표준기여_2992_260527","spend":10377,"purchases":1,"val":41000,"roas":395.1045581574636},{"name":"260403_HCP_FB_new_all_쌀때쟁이세요A_가격_할인율_이미지_prod_2464_ahi_og","product":"크리스피닭가슴살","person":"안혜인","camp":"07.크리스피(ASC)(메가딜)_A+SC 캠페인_구매최적화_수_표준기여_2464","spend":10171,"purchases":0,"val":0,"roas":0},{"name":"260621_HSL_FB_new_all_유정띠배너B_제품력_맛_릴스_prod_2996_ahi_og","product":"닭다리","person":"안혜인","camp":"03.닭다리살(ASC)(1010)_A+SC캠페인_구매최적화_수_표준기여_2604_260618_유정","spend":10099,"purchases":1,"val":54700,"roas":541.637785919398},{"name":"260621_HTR_FB_new_all_이게더맛있는데요_제품력_맛_릴스_prod_2903_bye_og","product":"안심폭탄볶음밥","person":"배영언","camp":"17.안심볶음밥(ASC)(메가딜)_TROAS_A+SC캠페인_구매최적화_값_표준기여_2903_260705","spend":10026,"purchases":1,"val":45900,"roas":457.8096947935368},{"name":"260517_HCPL_FB_new_all_또품절_가격_맛_릴스_prod_2910_ysy_og - 사본","product":"크리스피닭다리","person":"양서영","camp":"18.크리스피닭다리(ASC)_A+SC 캠페인_구매최적화_수_표준기여_2910_260416","spend":9806,"purchases":0,"val":0,"roas":0},{"name":"260621_HTG_FB_new_all_이걸로_맛_제품력_릴스_prod_3068_ljh_og","product":"통살+그릴드","person":"이지현","camp":"21.통살+그릴드(ASC)(메가딜)_A+SC캠페인_구매최적화_수_표준기여_3068_260617","spend":9272,"purchases":2,"val":119400,"roas":1287.7480586712684},{"name":"260621_HTR_FB_new_all_5분도안걸리는데_제품력_맛_릴스_prod_2903_bye_og","product":"안심폭탄볶음밥","person":"배영언","camp":"17.안심볶음밥(ASC)(메가딜)_TROAS_A+SC캠페인_구매최적화_값_표준기여_2903_260705","spend":7640,"purchases":0,"val":0,"roas":0},{"name":"260524_HDG_FB_new_all_전설의한끼통살_제품력_릴스_prod_2336_psh_og","product":"닭가슴살","person":"박시현","camp":"01.통살(ASC)(101010)_A+SC 캠페인_ALL_V1C7_수_표준기여_2336_AI","spend":7595,"purchases":0,"val":0,"roas":0},{"name":"260403_HCP_FB_new_all_비밀링크강조콘_가격_개당가격_이미지_prod_2464_ahi_og","product":"크리스피닭가슴살","person":"안혜인","camp":"07.크리스피(ASC)(통합)_A+SC 캠페인_구매최적화_수_표준기여_통합_260511","spend":6814,"purchases":0,"val":0,"roas":0},{"name":"260614_HDG_FB_new_all_큰일냄_구성_어전시_릴스_prod_3028_ljh_og","product":"닭가슴살","person":"이지현","camp":"01.통살(ASC)(하이브리드)_TROAS_A+SC캠페인_구매최적화_값_표준기여_3028_260611","spend":5996,"purchases":0,"val":0,"roas":0},{"name":"260531_HDG_FB_new_all_닭쳤어요_제품력_가격_릴스_prod_2336_kjy_og","product":"닭가슴살","person":"강주이","camp":"01.통살(ASC)(101010)_A+SC 캠페인_구매최적화_수_표준기여_2336_260410_intern","spend":5862,"purchases":0,"val":0,"roas":0},{"name":"260524_HCP_FB_new_all_사십오프로_가격_제품력_릴스_prod_2659_jhr_og","product":"크리스피닭가슴살","person":"정혜림","camp":"07.크리스피(ASC)(101010)_TCPA14000_A+SC 캠페인_ALL_C7_수_표준기여_2659_260424_intern","spend":4986,"purchases":0,"val":0,"roas":0},{"name":"260517_HTR_FB_new_all_안폭볶이미지8_제품력_맛_이미지_prod_2903_cjs_og","product":"안심폭탄볶음밥","person":"최진성","camp":"17.안심볶음밥(ASC)(메가딜)_TCPA_A+SC 캠페인_ALL_C7_수_표준기여_2903_260409","spend":4909,"purchases":0,"val":0,"roas":0},{"name":"260621_HSL_FB_new_all_유정세로띠배너A_제품력_맛_릴스_prod_2996_ahi_og","product":"닭다리","person":"안혜인","camp":"03.닭다리살(ASC)(1010)_A+SC캠페인_구매최적화_수_표준기여_2604_260618_유정","spend":4473,"purchases":0,"val":0,"roas":0},{"name":"260628_HCP_FB_new_all_우와_가격_맛_릴스_prod_2992_chy_og","product":"크리스피닭가슴살","person":"천혜영","camp":"07.크리스피(ASC)(1010)_A+SC캠페인_구매최적화_수_표준기여_2992_260527","spend":4350,"purchases":0,"val":0,"roas":0},{"name":"260607_HCP_FB_new_all_올여름_제품력_가격_릴스_prod_2464_chy_og","product":"크리스피닭가슴살","person":"천혜영","camp":"07.크리스피(ASC)(메가딜)_A+SC 캠페인_구매최적화_수_표준기여_2464_260416_intern","spend":3813,"purchases":0,"val":0,"roas":0},{"name":"260628_HTG_FB_new_all_자취생 냉동실_가격_제품력_릴스_prod_3068_ysy_og","product":"통살+그릴드","person":"양서영","camp":"21.통살+그릴드(ASC)(메가딜)_TROAS_A+SC캠페인_구매최적화_값_표준기여_3068_260617","spend":3674,"purchases":0,"val":0,"roas":0},{"name":"260607_HCP_FB_new_all_작정_제품력_가격_릴스_prod_2992_jhr_og","product":"크리스피닭가슴살","person":"정혜림","camp":"07.크리스피(ASC)(1010)_TCPA_A+SC캠페인_ALL_C7_수_표준기여_2992_260705","spend":3452,"purchases":0,"val":0,"roas":0},{"name":"260614_HCPL_FB_new_all_야르한거_신제품_제품력_릴스_prod_2910_ksr_og","product":"크리스피닭다리","person":"김승룡","camp":"18.크리스피닭다리(ASC)_TCPA14000_A+SC 캠페인_ALL_C7_수_표준기여_2910_260416","spend":3129,"purchases":0,"val":0,"roas":0},{"name":"260607_HSL_FB_new_all_당첨입니다_가격_제품력_릴스_prod_2358_jjy_og","product":"닭다리","person":"장지영","camp":"03.닭다리살(ASC)(101010)_A+SC 캠페인_구매최적화_수_표준기여_2358_260410_intern","spend":3124,"purchases":0,"val":0,"roas":0},{"name":"260517_HDG_FB_new_all_한끼통살3종_제품력_릴스_prod_2336_psh_og - 사본","product":"닭가슴살","person":"박시현","camp":"01.통살(ASC)(101010)_TCPA_A+SC 캠페인_ALL_C7_수_표준기여_2336_260410_intern","spend":2366,"purchases":0,"val":0,"roas":0},{"name":"260614_HCP_FB_new_all_더왔어요_가격_제품력_릴스_prod_2464_jhr_og","product":"크리스피닭가슴살","person":"정혜림","camp":"07.크리스피(ASC)(메가딜)_TCPA16000_A+SC 캠페인_ALL_수_표준기여_2464_260403","spend":2221,"purchases":0,"val":0,"roas":0},{"name":"260621_HSL_FB_new_all_유정세로띠배너B_제품력_영양성분_릴스_prod_2996_ahi_og","product":"닭다리","person":"안혜인","camp":"03.닭다리살(ASC)(1010)_A+SC캠페인_구매최적화_수_표준기여_2604_260618_유정","spend":2193,"purchases":0,"val":0,"roas":0},{"name":"260614_HCPT_FB_new_all_천재가 분명해_맛_제품력_릴스_prod_2908_ysy_og","product":"크리스피안심","person":"양서영","camp":"16.안심크리스피(ASC)(메가딜)_TROAS_A+SC 캠페인_구매최적화_값_표준기여_2908_260518","spend":2136,"purchases":0,"val":0,"roas":0},{"name":"260503_HTR_FB_new_all_3대500_제품력_가격_릴스_prod_2903_jhr_og","product":"안심폭탄볶음밥","person":"정혜림","camp":"17.안심볶음밥(ASC)(메가딜)_A+SC 캠페인_구매최적화_수_표준기여_2903_260609_남자(가치조정)","spend":1841,"purchases":0,"val":0,"roas":0},{"name":"260419_HCPL_FB_new_all_드디어_제품력_맛_릴스_prod_2910_ysy_og","product":"크리스피닭다리","person":"양서영","camp":"18.크리스피닭다리(ASC)_TCPA14000_A+SC 캠페인_ALL_C7_수_표준기여_2910_260416","spend":1736,"purchases":0,"val":0,"roas":0},{"name":"260531_HKBB_FB_new_all_정말조심_맛_릴스_prod_3003_psh_og","product":"김자반밥바","person":"박시현","camp":"20.김자반밥바(ASC)(메가딜)_TROAS_A+SC캠페인_구매최적화_값_표준기여_3003_260527","spend":1600,"purchases":0,"val":0,"roas":0},{"name":"260614_HCP_FB_new_all_야르한_맛_가격_릴스_prod_2992_chy_og","product":"크리스피닭가슴살","person":"천혜영","camp":"07.크리스피(ASC)(1010)_TROAS_A+SC캠페인_구매최적화_값_표준기여_2992_260527","spend":1340,"purchases":0,"val":0,"roas":0},{"name":"260621_HTR_FB_new_all_판매량1위_제품력_가격_릴스_prod_2903_bye_og","product":"안심폭탄볶음밥","person":"배영언","camp":"17.안심볶음밥(ASC)(메가딜)_TROAS_A+SC캠페인_구매최적화_값_표준기여_2903_260705","spend":1173,"purchases":0,"val":0,"roas":0},{"name":"260607_HCP_FB_new_all_이구성실화_가격_제품력_릴스_prod_2992_jhr_og","product":"크리스피닭가슴살","person":"정혜림","camp":"07.크리스피(ASC)(1010)_TROAS_A+SC캠페인_구매최적화_값_표준기여_2992_260527","spend":1169,"purchases":0,"val":0,"roas":0},{"name":"260524_HSL_FB_new_all_유행_가격_맛_릴스_prod_2358_jjy_og","product":"닭다리","person":"장지영","camp":"03.닭다리살(ASC)(101010)_A+SC 캠페인_구매최적화_값_표준기여_2358","spend":1118,"purchases":0,"val":0,"roas":0},{"name":"260517_HCPL_FB_new_all_와여러분_제품력_가격_릴스_prod_2910_jhr_og","product":"크리스피닭다리","person":"정혜림","camp":"18.크리스피닭다리(ASC)_A+SC 캠페인_구매최적화_수_표준기여_2910_260416_intern(광고소진후종료)","spend":968,"purchases":0,"val":0,"roas":0},{"name":"260621_HCP_FB_new_all_팩폭리뷰_맛_제품력_릴스_prod_2659_ksg_og","product":"크리스피닭가슴살","person":"김선길","camp":"07.크리스피(ASC)(101010)_TCPA14000_A+SC 캠페인_ALL_C7_수_표준기여_2659_260424_intern","spend":753,"purchases":0,"val":0,"roas":0},{"name":"260531_HCP_FB_new_all_기획세트_가격_제품력_릴스_prod_2992_jhr_og","product":"크리스피닭가슴살","person":"정혜림","camp":"07.크리스피(ASC)(1010)_TROAS_A+SC캠페인_구매최적화_값_표준기여_2992_260527","spend":649,"purchases":0,"val":0,"roas":0},{"name":"260607_HCPL_FB_new_all_왜참아요_제품력_맛_릴스_prod_2910_ksr_og","product":"크리스피닭다리","person":"김승룡","camp":"18.크리스피닭다리(ASC)_A+SC 캠페인_구매최적화_수_표준기여_2910_260416_intern(광고소진후종료)","spend":627,"purchases":0,"val":0,"roas":0},{"name":"260628_HCP_FB_new_all_이유_제품력_가격_릴스_prod_2992_chy_og","product":"크리스피닭가슴살","person":"천혜영","camp":"07.크리스피(ASC)(1010)_A+SC캠페인_구매최적화_수_표준기여_2992_260527","spend":624,"purchases":0,"val":0,"roas":0},{"name":"260614_HCPL_FB_new_all_드디어치킨_제품력_맛_릴스_prod_2910_ksr_og","product":"크리스피닭다리","person":"김승룡","camp":"18.크리스피닭다리(ASC)_TROAS_A+SC 캠페인_구매최적화_값_표준기여_2910_260518","spend":592,"purchases":0,"val":0,"roas":0},{"name":"260614_HDG_FB_new_all_식단러밥도둑_맛_제품력_릴스_prod_2336_kjy_og","product":"닭가슴살","person":"강주이","camp":"01.통살(ASC)(101010)_TCPA_A+SC 캠페인_ALL_C7_수_표준기여_2336_260410_intern","spend":575,"purchases":0,"val":0,"roas":0},{"name":"260524_HDG_FB_new_all_공익목적_제품력_가격_릴스_prod_2336_psh_og","product":"닭가슴살","person":"박시현","camp":"01.통살(ASC)(101010)_A+SC 캠페인_구매최적화_수_표준기여_2336_260410_intern","spend":559,"purchases":0,"val":0,"roas":0},{"name":"260531_HDG_FB_new_all_5초드림_제품력_릴스_prod_2336_kjy_og","product":"닭가슴살","person":"강주이","camp":"01.통살(ASC)(101010)_A+SC 캠페인_구매최적화_수_표준기여_2336_260410_intern","spend":549,"purchases":0,"val":0,"roas":0},{"name":"260614_HCP_FB_new_all_이정도까지_제품력_가격_릴스_prod_2992_chy_og","product":"크리스피닭가슴살","person":"천혜영","camp":"07.크리스피(ASC)(1010)_TROAS_A+SC캠페인_구매최적화_값_표준기여_2992_260527","spend":547,"purchases":0,"val":0,"roas":0},{"name":"260607_HDG_FB_new_all_누가만들었나요_맛_가격_릴스_prod_2336_kjy_og","product":"닭가슴살","person":"강주이","camp":"01.통살(ASC)(101010)_A+SC 캠페인_구매최적화_수_표준기여_2336_260410_intern","spend":543,"purchases":0,"val":0,"roas":0},{"name":"260607_HKBB_FB_new_all_벼르고있던_맛_제품력_릴스_prod_3003_psh_og","product":"김자반밥바","person":"박시현","camp":"20.김자반밥(ASC)(메가딜)_TCPA_A+SC캠페인_ALL_C7_수_표준기여_3003_260527","spend":524,"purchases":0,"val":0,"roas":0},{"name":"260628_HDG_FB_new_all_아니이게뭐야_가격_제품력_릴스_prod_3028_ysy_og","product":"닭가슴살","person":"양서영","camp":"01.통살(ASC)(하이브리드)_A+SC캠페인_구매최적화_수_표준기여_3028_260611","spend":464,"purchases":0,"val":0,"roas":0},{"name":"260403_HCP_FB_new_all_역대급신상_가격_개당가격_이미지_prod_2464_ahi_og","product":"크리스피닭가슴살","person":"안혜인","camp":"07.크리스피(ASC)(메가딜)_A+SC 캠페인_구매최적화_수_표준기여_2464","spend":460,"purchases":0,"val":0,"roas":0},{"name":"260517_HCPL_FB_new_all_또품절_가격_맛_릴스_prod_2910_ysy_og","product":"크리스피닭다리","person":"양서영","camp":"18.크리스피닭다리(ASC)_TCPA14000_A+SC 캠페인_ALL_C7_수_표준기여_2910_260416","spend":436,"purchases":0,"val":0,"roas":0},{"name":"260621_HTG_FB_new_all_지갑다털림_가격_제품력_릴스_prod_3068_ljh_og","product":"통살+그릴드","person":"이지현","camp":"21.통살+그릴드(ASC)(메가딜)_TCPA_A+SC캠페인_ALL_C7_수_표준기여_3068_260617","spend":422,"purchases":0,"val":0,"roas":0},{"name":"260426_HCP_FB_new_all_그치킨_제품력_가격_릴스_prod_2464_jjy_og","product":"크리스피닭가슴살","person":"장지영","camp":"07.크리스피(ASC)(메가딜)_TCPA14000_A+SC 캠페인_ALL_C7_수_표준기여_2464_260416_intern","spend":416,"purchases":0,"val":0,"roas":0},{"name":"260607_HKBB_FB_new_all_꼭사드세요_맛_릴스_prod_3003_psh_og","product":"김자반밥바","person":"박시현","camp":"20.김자반밥(ASC)(메가딜)_TCPA_A+SC캠페인_ALL_C7_수_표준기여_3003_260527","spend":396,"purchases":0,"val":0,"roas":0},{"name":"260517_HCP_FB_new_all_이거왜안사먹어요_가격_제품력_릴스_prod_2464_chy_og","product":"크리스피닭가슴살","person":"천혜영","camp":"07.크리스피(ASC)(메가딜)_TCPA16000_A+SC 캠페인_ALL_수_표준기여_2464_260403","spend":346,"purchases":0,"val":0,"roas":0},{"name":"260531_HCPT_FB_new_all_식단지원_가격_제품력_릴스_prod_2908_ysy_og","product":"크리스피안심","person":"양서영","camp":"16.안심크리스피(ASC)(메가딜)_TROAS_A+SC 캠페인_구매최적화_값_표준기여_2908_260518","spend":346,"purchases":0,"val":0,"roas":0},{"name":"260607_HCPT_FB_new_all_당황하지않고_맛_제품력_릴스_prod_2908_ysy_og","product":"크리스피안심","person":"양서영","camp":"16.안심크리스피(ASC)(메가딜)_TROAS_A+SC 캠페인_구매최적화_값_표준기여_2908_260518","spend":326,"purchases":0,"val":0,"roas":0},{"name":"260517_HCPL_FB_new_all_올여름_제품력_가격_릴스_prod_2910_ysy_og","product":"크리스피닭다리","person":"양서영","camp":"18.크리스피닭다리(ASC)_TCPA14000_A+SC 캠페인_ALL_C7_수_표준기여_2910_260416","spend":320,"purchases":0,"val":0,"roas":0},{"name":"260614_HDG_FB_new_all_주머니가벼운_가격_prod_2336_kjy_og","product":"닭가슴살","person":"강주이","camp":"01.통살(ASC)(101010)_TCPA_A+SC 캠페인_ALL_C7_수_표준기여_2336_260410_intern","spend":319,"purchases":0,"val":0,"roas":0},{"name":"260524_HCP_FB_new_all_성공했어요_제품력_가격_릴스_prod_2464_chy_og","product":"크리스피닭가슴살","person":"천혜영","camp":"07.크리스피(ASC)(메가딜)_A+SC 캠페인_구매최적화_수_표준기여_2464_260416_intern","spend":297,"purchases":0,"val":0,"roas":0},{"name":"260531_HSL_FB_new_all_끌고가는친구B_제품력_맛_릴스_prod_2358_jjy_og","product":"닭다리","person":"장지영","camp":"03.닭다리살(ASC)(101010)_A+SC 캠페인_구매최적화_수_표준기여_2358_260410_intern","spend":270,"purchases":0,"val":0,"roas":0},{"name":"260607_HCP_FB_new_all_이거맛없다는사람_맛_제품력_릴스_prod_2464_chy_og","product":"크리스피닭가슴살","person":"천혜영","camp":"07.크리스피(ASC)(메가딜)_TCPA16000_A+SC 캠페인_ALL_수_표준기여_2464_260403","spend":268,"purchases":0,"val":0,"roas":0},{"name":"260628_HDG_FB_new_all_요즘 경기에_가격_제품력_릴스_prod_3028_ysy_og","product":"닭가슴살","person":"양서영","camp":"01.통살(ASC)(하이브리드)_A+SC캠페인_구매최적화_수_표준기여_3028_260611","spend":256,"purchases":0,"val":0,"roas":0},{"name":"260621_HCP_FB_new_all_이런게있었어?_제품력_가격_릴스_prod_2992_chy_og","product":"크리스피닭가슴살","person":"천혜영","camp":"07.크리스피(ASC)(1010)_A+SC캠페인_구매최적화_수_표준기여_2992_260527","spend":247,"purchases":0,"val":0,"roas":0},{"name":"260607_HSL_FB_new_all_항의전화_제품력_가격_릴스_prod_2358_jjy_og","product":"닭다리","person":"장지영","camp":"03.닭다리살(ASC)(101010)_A+SC 캠페인_구매최적화_값_표준기여_2358","spend":219,"purchases":0,"val":0,"roas":0},{"name":"260621_HCPT_FB_new_all_이걸로 드세요_제품력_맛_릴스_prod_2908_ysy_og","product":"크리스피안심","person":"양서영","camp":"16.안심크리스피(ASC)(메가딜)_TCPA_A+SC캠페인_ALL_C7_수_표준기여_2908_260621","spend":192,"purchases":0,"val":0,"roas":0},{"name":"260628_HDG_FB_new_all_검색어 1위_가격_제품력_릴스_prod_3028_ysy_og","product":"닭가슴살","person":"양서영","camp":"01.통살(ASC)(하이브리드)_A+SC캠페인_구매최적화_수_표준기여_3028_260611","spend":183,"purchases":0,"val":0,"roas":0},{"name":"260531_HKBB_FB_new_all_와이게_제품력_맛_릴스_prod_3003_psh_og","product":"김자반밥바","person":"박시현","camp":"20.김자반밥바(ASC)(메가딜)_TROAS_A+SC캠페인_구매최적화_값_표준기여_3003_260527","spend":182,"purchases":0,"val":0,"roas":0},{"name":"260614_HCPT_FB_new_all_큰거왔어요_맛_제품력_릴스_prod_2908_ysy_og","product":"크리스피안심","person":"양서영","camp":"16.안심크리스피(ASC)(메가딜)_TROAS_A+SC 캠페인_구매최적화_값_표준기여_2908_260518","spend":175,"purchases":0,"val":0,"roas":0},{"name":"260607_HCP_FB_new_all_식단걱정끝_제품력_가격_릴스_prod_2464_chy_og","product":"크리스피닭가슴살","person":"천혜영","camp":"07.크리스피(ASC)(메가딜)_TCPA16000_A+SC 캠페인_ALL_수_표준기여_2464_260403","spend":173,"purchases":0,"val":0,"roas":0},{"name":"260531_HCP_FB_new_all_요즘_가격_제품력_릴스_prod_2992_jhr_og","product":"크리스피닭가슴살","person":"정혜림","camp":"07.크리스피(ASC)(1010)_TROAS_A+SC캠페인_구매최적화_값_표준기여_2992_260527","spend":166,"purchases":0,"val":0,"roas":0},{"name":"260531_HCP_FB_new_all_대체이게왜_제품력_가격_릴스_prod_2464_chy_og","product":"크리스피닭가슴살","person":"천혜영","camp":"07.크리스피(ASC)(메가딜)_TCPA16000_A+SC 캠페인_ALL_수_표준기여_2464_260403","spend":159,"purchases":0,"val":0,"roas":0},{"name":"260524_HCP_FB_new_all_식단템_가격_제품력_릴스_prod_2659_ksg_og","product":"크리스피닭가슴살","person":"김선길","camp":"07.크리스피(ASC)(101010)_TCPA14000_A+SC 캠페인_ALL_C7_수_표준기여_2659_260424_intern","spend":157,"purchases":0,"val":0,"roas":0},{"name":"260607_HCP_FB_new_all_고오맙다_맛_가격_릴스_prod_2992_jhr_og","product":"크리스피닭가슴살","person":"정혜림","camp":"07.크리스피(ASC)(1010)_TCPA_A+SC캠페인_ALL_C7_수_표준기여_2992_260705","spend":156,"purchases":0,"val":0,"roas":0},{"name":"260531_HDG_FB_new_all_이게뭐냐고요_제품력_릴스_prod_2336_kjy_og","product":"닭가슴살","person":"강주이","camp":"01.통살(ASC)(101010)_A+SC 캠페인_구매최적화_수_표준기여_2336_260410_intern","spend":149,"purchases":0,"val":0,"roas":0},{"name":"260621_HTG_FB_new_all_치밥식단_맛_제품력_릴스_prod_3068_ljh_og","product":"통살+그릴드","person":"이지현","camp":"21.통살+그릴드(ASC)(메가딜)_TROAS_A+SC캠페인_구매최적화_값_표준기여_3068_260617","spend":148,"purchases":0,"val":0,"roas":0},{"name":"260621_HSL_FB_new_all_유정띠배너C_제품력_영양성분_릴스_prod_2996_ahi_og","product":"닭다리","person":"안혜인","camp":"03.닭다리살(ASC)(1010)_A+SC캠페인_구매최적화_수_표준기여_2604_260618_유정","spend":146,"purchases":0,"val":0,"roas":0},{"name":"260531_HCPL_FB_new_all_지현님2분할_시즐고도_맛_릴스_prod_2910_ksr_og","product":"크리스피닭다리","person":"김승룡","camp":"18.크리스피닭다리(ASC)_A+SC 캠페인_구매최적화_수_표준기여_2910_260416_intern(광고소진후종료)","spend":136,"purchases":0,"val":0,"roas":0},{"name":"260510_HTR_FB_new_all_삼시세끼_제품력_맛_릴스_prod_2903_ksg_og","product":"안심폭탄볶음밥","person":"김선길","camp":"17.안심볶음밥(ASC)(메가딜)_A+SC 캠페인_구매최적화_수_표준기여_2903_260507_남자_02","spend":127,"purchases":0,"val":0,"roas":0},{"name":"260503_HDG_FB_new_all_작심삼일_제품력_가격_릴스_prod_2336_psh_og","product":"닭가슴살","person":"박시현","camp":"01.통살(ASC)(101010)_A+SC 캠페인_구매최적화_수_표준기여_2336_260410_intern","spend":119,"purchases":0,"val":0,"roas":0},{"name":"260607_HCP_FB_new_all_나마케터_제품력_가격_릴스_prod_2992_jhr_og","product":"크리스피닭가슴살","person":"정혜림","camp":"07.크리스피(ASC)(1010)_TCPA_A+SC캠페인_ALL_C7_수_표준기여_2992_260705","spend":116,"purchases":0,"val":0,"roas":0},{"name":"260517_HCPL_FB_new_all_친구네_제품력_가격_릴스_prod_2910_ysy_og","product":"크리스피닭다리","person":"양서영","camp":"18.크리스피닭다리(ASC)_TCPA14000_A+SC 캠페인_ALL_C7_수_표준기여_2910_260416","spend":112,"purchases":0,"val":0,"roas":0},{"name":"260614_HCP_FB_new_all_찾았어요혜택_가격_제품력_릴스_prod_2992_chy_og","product":"크리스피닭가슴살","person":"천혜영","camp":"07.크리스피(ASC)(1010)_TROAS_A+SC캠페인_구매최적화_값_표준기여_2992_260527","spend":105,"purchases":0,"val":0,"roas":0},{"name":"260531_HSL_FB_new_all_손해입니다_가격_제품력_릴스_prod_2358_jjy_og","product":"닭다리","person":"장지영","camp":"03.닭다리살(ASC)(101010)_A+SC 캠페인_구매최적화_수_표준기여_2358_260410_intern","spend":99,"purchases":0,"val":0,"roas":0},{"name":"260621_HCPL_FB_new_all_현미범벅_맛_신제품_릴스_prod_3069_ksr_og","product":"크리스피닭다리","person":"김승룡","camp":"18.크리스피닭다리(ASC)_A+SC 캠페인_구매최적화_수_표준기여_2910_260705","spend":98,"purchases":0,"val":0,"roas":0},{"name":"260517_HDG_FB_new_all_식단덕후_제품력_릴스_prod_2336_psh_og","product":"닭가슴살","person":"박시현","camp":"01.통살(ASC)(101010)_A+SC 캠페인_구매최적화_수_표준기여_2336_260410_intern","spend":96,"purchases":0,"val":0,"roas":0},{"name":"260517_HTR_FB_new_all_안폭볶이미지2_제품력_맛_이미지_prod_2903_cjs_og","product":"안심폭탄볶음밥","person":"최진성","camp":"17.안심볶음밥(ASC)(메가딜)_TCPA_A+SC 캠페인_ALL_C7_수_표준기여_2903_260409","spend":96,"purchases":0,"val":0,"roas":0},{"name":"260524_HTR_FB_new_all_3대500마케터_가격_제품력_릴스_prod_2903_bye_og","product":"안심폭탄볶음밥","person":"배영언","camp":"17.안심볶음밥(ASC)(메가딜)_TCPA_A+SC 캠페인_ALL_C7_수_표준기여_2903_260409","spend":87,"purchases":0,"val":0,"roas":0},{"name":"260614_HCP_FB_new_all_누워서_제품력_가격_릴스_prod_2464_jhr_og","product":"크리스피닭가슴살","person":"정혜림","camp":"07.크리스피(ASC)(메가딜)_TCPA16000_A+SC 캠페인_ALL_수_표준기여_2464_260403","spend":86,"purchases":0,"val":0,"roas":0},{"name":"260412_HDG_FB_new_all_아니이게뭐야_맛_가격_prod_2336_sys_og","product":"닭가슴살","person":"송예서","camp":"01.통살(ASC)(101010)_TCPA16000_A+SC 캠페인_ALL_V1C7_수_표준기여_2336","spend":80,"purchases":0,"val":0,"roas":0},{"name":"260524_HSL_FB_new_all_100원_가격_할인율_릴스_prod_2358_jjy_og","product":"닭다리","person":"장지영","camp":"03.닭다리살(ASC)(101010)_A+SC 캠페인_구매최적화_수_표준기여_2358_260410_intern","spend":78,"purchases":0,"val":0,"roas":0},{"name":"260614_HSL_FB_new_all_빨리이유_맛_제품력_릴스_prod_2358_jjy_og","product":"닭다리","person":"장지영","camp":"03.닭다리살(ASC)(101010)_A+SC 캠페인_구매최적화_값_표준기여_2358","spend":78,"purchases":0,"val":0,"roas":0},{"name":"260531_HDG_FB_new_all_야르_맛_릴스_prod_2336_kjy_og","product":"닭가슴살","person":"강주이","camp":"01.통살(ASC)(101010)_A+SC 캠페인_구매최적화_수_표준기여_2336_260410_intern","spend":77,"purchases":0,"val":0,"roas":0},{"name":"260531_HCPT_FB_new_all_취소하게 만드는_맛_제품력_릴스_prod_2908_ysy_og","product":"크리스피안심","person":"양서영","camp":"16.안심크리스피(ASC)(메가딜)_TROAS_A+SC 캠페인_구매최적화_값_표준기여_2908_260518","spend":69,"purchases":0,"val":0,"roas":0},{"name":"260524_HSL_FB_new_all_식단할사람_가격_할인율_릴스_prod_2358_jjy_og","product":"닭다리","person":"장지영","camp":"03.닭다리살(ASC)(101010)_A+SC 캠페인_구매최적화_수_표준기여_2358_260410_intern","spend":67,"purchases":0,"val":0,"roas":0},{"name":"260517_HCPL_FB_new_all_닭치맛강조콘_맛_영양성분_이미지_prod_2910_ahi_og - 사본","product":"크리스피닭다리","person":"안혜인","camp":"18.크리스피닭다리(ASC)_TCPA14000_A+SC 캠페인_ALL_C7_수_표준기여_2910_260416","spend":57,"purchases":0,"val":0,"roas":0},{"name":"260524_HSL_FB_new_all_자취생_가격_제품력_릴스_prod_2358_jjy_og","product":"닭다리","person":"장지영","camp":"03.닭다리살(ASC)(101010)_A+SC 캠페인_구매최적화_수_표준기여_2358_260410_intern","spend":53,"purchases":0,"val":0,"roas":0},{"name":"260621_HTG_FB_new_all_도랏미쳣_구성_어전시_릴스_prod_3068_ljh_og","product":"통살+그릴드","person":"이지현","camp":"21.통살+그릴드(ASC)(메가딜)_TCPA_A+SC캠페인_ALL_C7_수_표준기여_3068_260617","spend":50,"purchases":0,"val":0,"roas":0},{"name":"260412_HDG_FB_new_all_이것만먹을거에요_맛_제품력_prod_2336_sys_og","product":"닭가슴살","person":"송예서","camp":"01.통살(ASC)(101010)_TCPA16000_A+SC 캠페인_ALL_V1C7_수_표준기여_2336","spend":47,"purchases":0,"val":0,"roas":0},{"name":"260531_HSL_FB_new_all_3종_가격_맛_릴스_prod_2358_jjy_og","product":"닭다리","person":"장지영","camp":"03.닭다리살(ASC)(101010)_A+SC 캠페인_구매최적화_수_표준기여_2358_260410_intern","spend":43,"purchases":0,"val":0,"roas":0},{"name":"260524_HCP_FB_new_all_친구에게공유하세요_가격_제품력_릴스_prod_2464_chy_og","product":"크리스피닭가슴살","person":"천혜영","camp":"07.크리스피(ASC)(메가딜)_TCPA16000_A+SC 캠페인_ALL_수_표준기여_2464_260403","spend":36,"purchases":0,"val":0,"roas":0},{"name":"260426_HCP_FB_new_all_공구인플특가_가격_할인율_릴스_prod_2464_ahi_og","product":"크리스피닭가슴살","person":"안혜인","camp":"07.크리스피(ASC)(메가딜)_A+SC 캠페인_구매최적화_수_표준기여_2464","spend":33,"purchases":0,"val":0,"roas":0},{"name":"260403_HCP_FB_new_all_쌀때쟁이세요B_가격_개당가격_이미지_prod_2464_ahi_og","product":"크리스피닭가슴살","person":"안혜인","camp":"07.크리스피(ASC)(메가딜)_A+SC 캠페인_구매최적화_수_표준기여_2464","spend":31,"purchases":0,"val":0,"roas":0},{"name":"260426_HDG_FB_new_all_양념치킨_맛_가격_릴스_prod_2336_ljh_og - 사본","product":"닭가슴살","person":"이지현","camp":"01.통살(ASC)(101010)_TCPA16000_A+SC 캠페인_ALL_V1C7_수_표준기여_2336_02","spend":28,"purchases":0,"val":0,"roas":0},{"name":"260614_HSL_FB_new_all_빨리혜택_혜택_제품력_릴스_prod_2358_jjy_og","product":"닭다리","person":"장지영","camp":"03.닭다리살(ASC)(101010)_A+SC 캠페인_구매최적화_수_표준기여_2358_260410_intern","spend":23,"purchases":0,"val":0,"roas":0},{"name":"260517_HCP_FB_new_all_이거 진짜 맛있을까_맛_가격_릴스_prod_2464_chy_og","product":"크리스피닭가슴살","person":"천혜영","camp":"07.크리스피(ASC)(메가딜)_TCPA16000_A+SC 캠페인_ALL_수_표준기여_2464_260403","spend":21,"purchases":0,"val":0,"roas":0},{"name":"260621_HCPL_FB_new_all_드뎌먹어봤어요_대세감_제품력_릴스_prod_2910_ksr_og","product":"크리스피닭다리","person":"김승룡","camp":"18.크리스피닭다리(ASC)_TROAS_A+SC 캠페인_구매최적화_값_표준기여_2910_260518","spend":19,"purchases":0,"val":0,"roas":0},{"name":"260607_HSL_FB_new_all_찐리뷰콘_맛_제품력_릴스_prod_2358_jjy_og","product":"닭다리","person":"장지영","camp":"03.닭다리살(ASC)(101010)_A+SC 캠페인_구매최적화_수_표준기여_2358_260410_intern","spend":17,"purchases":0,"val":0,"roas":0},{"name":"260524_HCP_FB_new_all_드디어특가떴네요_가격_제품력_릴스_prod_2464_chy_og","product":"크리스피닭가슴살","person":"천혜영","camp":"07.크리스피(ASC)(메가딜)_A+SC 캠페인_구매최적화_수_표준기여_2464_260416_intern","spend":15,"purchases":0,"val":0,"roas":0},{"name":"260614_HKBB_FB_new_all_침고인다_맛_제품력_맛_릴스_prod_3003_psh_og","product":"김자반밥바","person":"박시현","camp":"20.김자반밥(ASC)(메가딜)_TCPA_A+SC캠페인_ALL_C7_수_표준기여_3003_260527","spend":12,"purchases":0,"val":0,"roas":0},{"name":"260510_HCP_FB_new_all_PT쌤도인정_제품력_가격_릴스_prod_2464_chy_og - 사본","product":"크리스피닭가슴살","person":"천혜영","camp":"07.크리스피(ASC)(메가딜)_A+SC 캠페인_구매최적화_수_표준기여_2464_260416_intern","spend":11,"purchases":0,"val":0,"roas":0},{"name":"260614_HSL_FB_new_all_속삭임_제품력_가격_릴스_prod_2358_jjy_og","product":"닭다리","person":"장지영","camp":"03.닭다리살(ASC)(101010)_A+SC 캠페인_구매최적화_수_표준기여_2358_260410_intern","spend":11,"purchases":0,"val":0,"roas":0},{"name":"260614_HTR_FB_new_all_형님들이만약_제품력_가격_릴스_prod_2903_bye_og","product":"안심폭탄볶음밥","person":"배영언","camp":"17.안심볶음밥(ASC)(메가딜)_A+SC 캠페인_구매최적화_수_표준기여_2903_260609_남자(가치조정)","spend":11,"purchases":0,"val":0,"roas":0},{"name":"260621_HCPL_FB_new_all_드뎌먹어봤어요_대세감_제품력_릴스_prod_3069_ksr_og","product":"크리스피닭다리","person":"김승룡","camp":"18.크리스피닭다리(ASC)_TCPA14000_A+SC 캠페인_ALL_C7_수_표준기여_2910_260705","spend":6,"purchases":0,"val":0,"roas":0},{"name":"260419_HCP_FB_new_all_치킨참다폭주하지마세요A_가격_비밀링크_릴스_prod_2464_chy_og","product":"크리스피닭가슴살","person":"천혜영","camp":"07.크리스피(ASC)(메가딜)_TCPA14000_A+SC 캠페인_ALL_C7_수_표준기여_2464_260416_intern","spend":5,"purchases":0,"val":0,"roas":0},{"name":"260412_HDG_FB_new_all_부담없죠_맛_영양성분_릴스_prod_2336_ljh_og","product":"닭가슴살","person":"이지현","camp":"01.통살(ASC)(101010)_TCPA16000_A+SC 캠페인_ALL_V1C7_수_표준기여_2336","spend":3,"purchases":0,"val":0,"roas":0},{"name":"260531_HCP_FB_new_all_1억개_가격_제품력_릴스_prod_2464_chy_og","product":"크리스피닭가슴살","person":"천혜영","camp":"07.크리스피(ASC)(메가딜)_A+SC 캠페인_구매최적화_수_표준기여_2464_260416_intern","spend":3,"purchases":0,"val":0,"roas":0},{"name":"260427_HDG_FB_new_all_할인에목숨걺3_가격_할인율_릴스_prod_2336_bye_ai_h_","product":"닭가슴살","person":"담당자 미확인","camp":"01.통살(ASC)(101010)_A+SC 캠페인_ALL_V1C7_수_표준기여_2336_AI","spend":0,"purchases":0,"val":0,"roas":0},{"name":"260503_HCP_FB_new_all_크리스피사과문_가격_할인율_릴스_prod_2659_ahi_og","product":"크리스피닭가슴살","person":"안혜인","camp":"07.크리스피(ASC)(101010)_A+SC 캠페인_구매최적화_수_표준기여_2659_02","spend":0,"purchases":0,"val":0,"roas":0},{"name":"260524_HCP_FB_new_all_검색해도_가격_제품력_릴스_prod_2659_jhr_og","product":"크리스피닭가슴살","person":"정혜림","camp":"07.크리스피(ASC)(101010)_TCPA14000_A+SC 캠페인_ALL_C7_수_표준기여_2659_260424_intern","spend":0,"purchases":0,"val":0,"roas":0},{"name":"260524_HSL_FB_new_all_여러분저찾았어요_제품력_맛_릴스_prod_2996_ahi_og","product":"닭다리","person":"안혜인","camp":"03.닭다리살(ASC)(1010)_TCPA_A+SC캠페인_ALL_C7_수_표준기여_2604_260519","spend":0,"purchases":0,"val":0,"roas":0},{"name":"260524_HSL_FB_new_all_상상의심텐텐_제품력_맛_릴스_prod_2996_ahi_og","product":"닭다리","person":"안혜인","camp":"03.닭다리살(ASC)(1010)_TCPA_A+SC캠페인_ALL_C7_수_표준기여_2604_260519","spend":0,"purchases":0,"val":0,"roas":0},{"name":"260607_HCPT_FB_new_all_이퀄리티_가격_제품력_릴스_prod_2908_ysy_og","product":"크리스피안심","person":"양서영","camp":"16.안심크리스피(ASC)(메가딜)_TROAS_A+SC 캠페인_구매최적화_값_표준기여_2908_260518","spend":0,"purchases":0,"val":0,"roas":0},{"name":"260607_HDG_FB_new_all_당장집어_제품력_릴스_prod_2336_kjy_og","product":"닭가슴살","person":"강주이","camp":"01.통살(ASC)(101010)_A+SC 캠페인_구매최적화_수_표준기여_2336_260410_intern","spend":0,"purchases":0,"val":0,"roas":0},{"name":"260517_HTR_FB_new_all_단돈100원_가격_제품력_릴스_prod_2903_bye_og","product":"안심폭탄볶음밥","person":"배영언","camp":"17.안심볶음밥(ASC)(메가딜)_A+SC 캠페인_구매최적화_수_표준기여_2903_260609_남자(가치조정)","spend":0,"purchases":0,"val":0,"roas":0},{"name":"260531_HCPT_FB_new_all_치킨의탈_맛_가격_릴스_prod_2908_ysy_og","product":"크리스피안심","person":"양서영","camp":"16.안심크리스피(ASC)(메가딜)_A+SC 캠페인_구매최적화_수_표준기여_2863_260327","spend":0,"purchases":0,"val":0,"roas":0},{"name":"260614_HDG_FB_new_all_주머니세상에_가격_릴스_prod_2336_kjy_og","product":"닭가슴살","person":"강주이","camp":"01.통살(ASC)(101010)_TCPA_A+SC 캠페인_ALL_C7_수_표준기여_2336_260410_intern","spend":0,"purchases":0,"val":0,"roas":0},{"name":"260614_HCP_FB_new_all_돈없는_제품력_가격_릴스_prod_2464_jhr_og","product":"크리스피닭가슴살","person":"정혜림","camp":"07.크리스피(ASC)(메가딜)_TCPA16000_A+SC 캠페인_ALL_수_표준기여_2464_260403","spend":0,"purchases":0,"val":0,"roas":0},{"name":"260614_HCP_FB_new_all_지난번소개_제품력_가격_릴스_prod_2659_ksg_og","product":"크리스피닭가슴살","person":"김선길","camp":"07.크리스피(ASC)(101010)_TCPA14000_A+SC 캠페인_ALL_C7_수_표준기여_2659_260322","spend":0,"purchases":0,"val":0,"roas":0},{"name":"260621_HTG_FB_new_all_일냈는데요_가격_구성_릴스_prod_3068_ljh_og","product":"통살+그릴드","person":"이지현","camp":"21.통살+그릴드(ASC)(메가딜)_A+SC캠페인_구매최적화_수_표준기여_3068_260617","spend":0,"purchases":0,"val":0,"roas":0},{"name":"260621_HCPL_FB_new_all_살려줘요_맛_가격_릴스_prod_3069_ksr_og","product":"크리스피닭다리","person":"김승룡","camp":"18.크리스피닭다리(ASC)_TCPA14000_A+SC 캠페인_ALL_C7_수_표준기여_2910_260705","spend":0,"purchases":0,"val":0,"roas":0}],"byPerson":[{"name":"안혜인","spend":2716375,"purchases":138,"val":6821692,"roas":251.13218903870046},{"name":"천혜영","spend":831538,"purchases":37,"val":2664286,"roas":320.404599669528},{"name":"이지현","spend":642257,"purchases":27,"val":1814700,"roas":282.5504432026432},{"name":"박시현","spend":504916,"purchases":31,"val":1297400,"roas":256.95363189124527},{"name":"김승룡","spend":380087,"purchases":12,"val":741400,"roas":195.06060454580137},{"name":"배영언","spend":378199,"purchases":17,"val":1334400,"roas":352.8301238237013},{"name":"정혜림","spend":235255,"purchases":13,"val":753900,"roas":320.46077660411044},{"name":"양서영","spend":222605,"purchases":5,"val":229200,"roas":102.96264684081669},{"name":"장지영","spend":153289,"purchases":5,"val":345000,"roas":225.06507316245785},{"name":"담당자 미확인","spend":127187,"purchases":1,"val":182300,"roas":143.3322588000346},{"name":"강주이","spend":51892,"purchases":1,"val":59800,"roas":115.23934325136823},{"name":"김선길","spend":45320,"purchases":0,"val":0,"roas":0},{"name":"최진성","spend":5005,"purchases":0,"val":0,"roas":0},{"name":"송예서","spend":127,"purchases":0,"val":0,"roas":0}]}